Workbook

Sheet ARV_Clean_Data
B2: ID | C2: PO / SO # | D2: ASN/DN # | E2: Country | F2: Product Group | G2: Sub Classification | H2: Vendor | I2: Fulfill Via | J2: Vendor INCO Term | K2: Shipment Mode | L2: PO Sent to Vendor Date | M2: Scheduled Delivery Date | N2: Delivered to Client Date | O2: Delivery Recorded Date | P2: Item Description | Q2: Molecule/Test Type | R2: Brand | S2: Dosage | T2: Dosage Form | U2: Unit of Measure (Per Pack) | V2: Line Item Quantity | W2: Line Item Value | X2: Pack Price | Y2: Unit Price | Z2: Weight (Kilograms) | AA2: Freight Cost (USD) | AB2: On_time_flag | AC2: Delivery Recorded Date - Copy
B3: 45 | C3: SCMS-140 | D3: ASN-94 | E3: Tanzania | F3: ARV | G3: Adult | H3: Aurobindo Pharma Limited | I3: Direct Drop | J3: EXW | K3: Air | M3: 39045 | N3: 39045 | O3: 39045 | P3: Nevirapine 200mg, tablets, 60 Tabs | Q3: Nevirapine | R3: Generic | S3: 200mg | T3: Tablet | U3: 60 | V3: 16667 | W3: 60834.55 | X3: 3.65 | Y3: 0.06 | Z3: 1478 | AA3: 6212.41 | AB3: 1 | AC3: 2006 | AE3: {=+(tblARV[Line Item Quantity]*tblARV[Unit Price])} -> 1000.02
B4: 64 | C4: SCMS-268 | D4: ASN-242 | E4: Rwanda | F4: ARV | G4: Adult | H4: CIPLA LIMITED | I4: Direct Drop | J4: EXW | K4: Air | L4: 39073 | M4: 39140 | N4: 39140 | O4: 39140 | P4: Lamivudine/Zidovudine 150/300mg, tablets, 60 Tabs | Q4: Lamivudine/Zidovudine | R4: Generic | S4: 150/300mg | T4: Tablet - FDC | U4: 60 | V4: 10000 | W4: 99800 | X4: 9.98 | Y4: 0.17 | Z4: 7416 | AA4: 64179.42 | AB4: 1 | AC4: 2007 | AE4: 1700
B5: 87 | C5: SCMS-555 | D5: ASN-409 | E5: Tanzania | F5: ARV | G5: Pediatric | H5: BRISTOL-MYERS SQUIBB | I5: Direct Drop | J5: CIP | K5: Air | L5: 39184 | M5: 39239 | N5: 39239 | O5: 39239 | P5: Didanosine 2g [Videx], powder for oral solution 10mg/ml, reconstitute to 200 ml | Q5: Didanosine | R5: Videx | S5: 2g | T5: Powder for oral solution | U5: 200 | V5: 712 | W5: 8964.08 | X5: 12.59 | Y5: 0.06 | Z5: 162 | AA5: 912.96 | AB5: 1 | AC5: 2007 | AE5: 42.72
B6: 161 | C6: SCMS-11070 | D6: ASN-916 | E6: Ethiopia | F6: ARV | G6: Adult | H6: Aurobindo Pharma Limited | I6: Direct Drop | J6: EXW | K6: Air | L6: 39358 | M6: 39406 | N6: 39406 | O6: 39406 | P6: Stavudine 30mg, capsules, 60 Caps | Q6: Stavudine | R6: Generic | S6: 30mg | T6: Capsule | U6: 60 | V6: 64000 | W6: 99200 | X6: 1.55 | Y6: 0.03 | Z6: 4228 | AA6: 12237.61 | AB6: 1 | AC6: 2007 | AE6: 1920
B7: 535 | C7: SCMS-23610 | D7: ASN-2167 | E7: Tanzania | F7: ARV | G7: Adult | H7: BRISTOL-MYERS SQUIBB | I7: Direct Drop | J7: CIP | K7: Air | L7: 39583 | M7: 39693 | N7: 39693 | O7: 39693 | P7: Didanosine EC 400mg [Videx EC], delayed-release capsules, Blister 3 x 10 Caps | Q7: Didanosine EC | R7: Videx EC | S7: 400mg | T7: Delayed-release capsules - blister | U7: 30 | V7: 2597 | W7: 61470.99 | X7: 23.67 | Y7: 0.79 | Z7: 117 | AA7: 645.1 | AB7: 1 | AC7: 2008 | AE7: 2051.63
B8: 858 | C8: SCMS-34680 | D8: ASN-3332 | E8: Tanzania | F8: ARV | G8: Adult | H8: MERCK SHARP & DOHME IDEA GMBH (FORMALLY MERCK SHARP & DOHME B.V.) | I8: Direct Drop | J8: CIP | K8: Air | L8: 39801 | M8: 39924 | N8: 39924 | O8: 39924 | P8: Efavirenz/Emtricitabine/Tenofovir Disoproxil Fumarate 600/200/300mg [Atripla], tablets, 30 Tabs | Q8: Efavirenz/Emtricitabine/Tenofovir Disoproxil Fumarate | R8: Atripla | S8: 600/200/300mg | T8: Tablet - FDC | U8: 30 | V8: 50000 | W8: 2520000 | X8: 50.4 | Y8: 1.68 | Z8: 4093 | AA8: 9339 | AB8: 1 | AC8: 2009 | AE8: 84000
B9: 985 | C9: SCMS-38370 | D9: ASN-3751 | E9: Tanzania | F9: ARV | G9: Pediatric | H9: ABBVIE LOGISTICS (FORMERLY ABBOTT LOGISTICS BV) | I9: Direct Drop | J9: FCA | K9: Air | L9: 39849 | M9: 39961 | N9: 39961 | O9: 39961 | P9: Lopinavir/Ritonavir 80/20mg/ml [Kaletra], oral solution, cool, Bottle 5 x 60 ml | Q9: Lopinavir/Ritonavir | R9: Kaletra | S9: 80/20mg/ml | T9: Oral solution | U9: 300 | V9: 524 | W9: 21536.4 | X9: 41.1 | Y9: 0.14 | Z9: 644 | AA9: 6668.61 | AB9: 1 | AC9: 2009 | AE9: 73.36
B10: 986 | C10: SCMS-38380 | D10: ASN-3627 | E10: Tanzania | F10: ARV | G10: Pediatric | H10: ABBVIE LOGISTICS (FORMERLY ABBOTT LOGISTICS BV) | I10: Direct Drop | J10: FCA | K10: Air | L10: 39849 | M10: 39937 | N10: 39937 | O10: 39937 | P10: Lopinavir/Ritonavir 100/25mg [Aluvia], tablets, 60 Tabs | Q10: Lopinavir/Ritonavir | R10: Generic | S10: 100/25mg | T10: Tablet | U10: 60 | V10: 2094 | W10: 21526.32 | X10: 10.28 | Y10: 0.17 | Z10: 237 | AB10: 1 | AC10: 2009 | AE10: 355.98
B11: 1156 | C11: SCMS-43890 | D11: ASN-4503 | E11: Rwanda | F11: ARV | G11: Adult | H11: HETERO LABS LIMITED | I11: Direct Drop | J11: CIP | K11: Air | L11: 39918 | M11: 40019 | N11: 40019 | O11: 40019 | P11: Efavirenz 600mg, tablets, 30 Tabs | Q11: Efavirenz | R11: Generic | S11: 600mg | T11: Tablet | U11: 30 | V11: 55356 | W11: 386384.88 | X11: 6.98 | Y11: 0.23 | Z11: 4482 | AA11: 37404.74 | AB11: 1 | AC11: 2009 | AE11: 12731.88
B12: 1299 | C12: SCMS-268 | D12: ASN-242 | E12: Rwanda | F12: ARV | G12: Adult | H12: CIPLA LIMITED | I12: Direct Drop | J12: EXW | K12: Air | L12: 39073 | M12: 39140 | N12: 39140 | O12: 39140 | P12: Efavirenz 600mg, tablets, 30 Tabs | Q12: Efavirenz | R12: Generic | S12: 600mg | T12: Tablet | U12: 30 | V12: 71577 | W12: 1087970.4 | X12: 15.2 | Y12: 0.51 | AB12: 1 | AC12: 2007 | AE12: 36504.27
B13: 1300 | C13: SCMS-268 | D13: ASN-242 | E13: Rwanda | F13: ARV | G13: Adult | H13: CIPLA LIMITED | I13: Direct Drop | J13: EXW | K13: Air | L13: 39073 | M13: 39140 | N13: 39140 | O13: 39140 | P13: Abacavir 300mg, tablets, 60 Tabs | Q13: Abacavir | R13: Generic | S13: 300mg | T13: Tablet | U13: 60 | V13: 5605 | W13: 202340.5 | X13: 36.1 | Y13: 0.6 | AB13: 1 | AC13: 2007 | AE13: 3363
B14: 1502 | C14: SCMS-13900 | D14: ASN-990 | E14: Rwanda | F14: ARV | G14: Adult | H14: ASPEN PHARMACARE | I14: Direct Drop | J14: EXW | K14: Air | L14: 39398 | M14: 39475 | N14: 39475 | O14: 39475 | P14: Tenofovir Disoproxil Fumarate 300mg [Viread], tablets, 30 Tabs | Q14: Tenofovir Disoproxil Fumarate | R14: Viread | S14: 300mg | T14: Tablet | U14: 30 | V14: 1609 | W14: 27353 | X14: 17 | Y14: 0.57 | Z14: 157 | AA14: 7922.24 | AB14: 1 | AC14: 2008 | AE14: 917.13
B15: 1529 | C15: SCMS-14750 | D15: ASN-1194 | E15: Rwanda | F15: ARV | G15: Adult | H15: MYLAN LABORATORIES LTD (FORMERLY MATRIX LABORATORIES) | I15: Direct Drop | J15: CIP | K15: Air | L15: 39419 | M15: 39475 | N15: 39475 | O15: 39475 | P15: Abacavir 300mg, tablets, 60 Tabs | Q15: Abacavir | R15: Generic | S15: 300mg | T15: Tablet | U15: 60 | V15: 1099 | W15: 30222.5 | X15: 27.5 | Y15: 0.46 | Z15: 113 | AA15: 1511.25 | AB15: 1 | AC15: 2008 | AE15: 505.54
B16: 1888 | C16: SCMS-25520 | D16: ASN-2079 | E16: Rwanda | F16: ARV | G16: Adult | H16: Aurobindo Pharma Limited | I16: Direct Drop | J16: CIP | K16: Air | L16: 39612 | M16: 39652 | N16: 39651 | O16: 39651 | P16: Lamivudine/Nevirapine/Zidovudine 150/200/300mg, tablets, 60 Tabs | Q16: Lamivudine/Nevirapine/Zidovudine | R16: Generic | S16: 150/300/200mg | T16: Tablet - FDC | U16: 60 | V16: 47879 | W16: 569281.31 | X16: 11.89 | Y16: 0.2 | Z16: 5311 | AA16: 30408.04 | AB16: 1 | AC16: 2008 | AE16: 9575.8
B17: 1889 | C17: SCMS-25520 | D17: ASN-2080 | E17: Rwanda | F17: ARV | G17: Adult | H17: Aurobindo Pharma Limited | I17: Direct Drop | J17: CIP | K17: Air | L17: 39612 | M17: 39652 | N17: 39652 | O17: 39652 | P17: Lamivudine/Nevirapine/Zidovudine 150/200/300mg, tablets, 60 Tabs | Q17: Lamivudine/Nevirapine/Zidovudine | R17: Generic | S17: 150/300/200mg | T17: Tablet - FDC | U17: 60 | V17: 61021 | W17: 725539.69 | X17: 11.89 | Y17: 0.2 | Z17: 6768 | AA17: 38120.96 | AB17: 1 | AC17: 2008 | AE17: 12204.2
B18: 2441 | C18: SCMS-41240 | D18: ASN-3904 | E18: Uganda | F18: ARV | G18: Adult | H18: BRISTOL-MYERS SQUIBB | I18: Direct Drop | J18: CIP | K18: Air | L18: 39891 | M18: 39937 | N18: 39937 | O18: 39937 | P18: Didanosine EC 250mg [Videx EC], delayed-release capsules, Blister 3 x 10 Caps | Q18: Didanosine EC | R18: Videx EC | S18: 250mg | T18: Delayed-release capsules - blister | U18: 30 | V18: 60 | W18: 1100.4 | X18: 18.34 | Y18: 0.61 | Z18: 3000 | AA18: 428.91 | AB18: 1 | AC18: 2009 | AE18: 36.6
B19: 2463 | C19: SCMS-30312 | D19: ASN-3851 | E19: Rwanda | F19: ARV | G19: Adult | H19: CIPLA LIMITED | I19: Direct Drop | J19: CIP | K19: Air | L19: 39742 | M19: 39923 | N19: 39923 | O19: 39923 | P19: Lamivudine/Zidovudine 150/300mg, tablets, 60 Tabs | Q19: Lamivudine/Zidovudine | R19: Generic | S19: 150/300mg | T19: Tablet - FDC | U19: 60 | V19: 7840 | W19: 71344 | X19: 9.1 | Y19: 0.15 | Z19: 719 | AA19: 853.88 | AB19: 1 | AC19: 2009 | AE19: 1176
B20: 2536 | C20: SCMS-43880 | D20: ASN-4462 | E20: Rwanda | F20: ARV | G20: Adult | H20: MYLAN LABORATORIES LTD (FORMERLY MATRIX LABORATORIES) | I20: Direct Drop | J20: CIP | K20: Air | L20: 39918 | M20: 40014 | N20: 40014 | O20: 40014 | P20: Lamivudine/Nevirapine/Zidovudine 150/200/300mg, tablets, 60 Tabs | Q20: Lamivudine/Nevirapine/Zidovudine | R20: Generic | S20: 150/300/200mg | T20: Tablet - FDC | U20: 60 | V20: 26932 | W20: 317528.28 | X20: 11.79 | Y20: 0.2 | Z20: 3393 | AA20: 30661.5 | AB20: 1 | AC20: 2009 | AE20: 5386.4
B21: 2808 | C21: SCMS-11071 | D21: ASN-1039 | E21: Ethiopia | F21: ARV | G21: Adult | H21: Aurobindo Pharma Limited | I21: Direct Drop | J21: EXW | K21: Air | L21: 39358 | M21: 39406 | N21: 39440 | O21: 39440 | P21: Stavudine 30mg, capsules, 60 Caps | Q21: Stavudine | R21: Generic | S21: 30mg | T21: Capsule | U21: 60 | V21: 35065 | W21: 54350.75 | X21: 1.55 | Y21: 0.03 | Z21: 2318 | AA21: 6755.81 | AB21: 0 | AC21: 2007 | AE21: 1051.95
B22: 2892 | C22: SCMS-13510 | D22: ASN-1483 | E22: Uganda | F22: ARV | G22: Adult | H22: BRISTOL-MYERS SQUIBB | I22: Direct Drop | J22: CIP | K22: Air | L22: 39358 | M22: 39538 | N22: 39538 | O22: 39538 | P22: Didanosine EC 400mg [Videx EC], delayed-release capsules, Blister 3 x 10 Caps | Q22: Didanosine EC | R22: Videx EC | S22: 400mg | T22: Delayed-release capsules - blister | U22: 30 | V22: 140 | W22: 3313.8 | X22: 23.67 | Y22: 0.79 | Z22: 6 | AB22: 1 | AC22: 2008 | AE22: 110.6
B23: 3294 | C23: SCMS-27190 | D23: ASN-2391 | E23: Uganda | F23: ARV | G23: Adult | H23: BRISTOL-MYERS SQUIBB | I23: Direct Drop | J23: CIP | K23: Air | L23: 39647 | M23: 39700 | N23: 39700 | O23: 39700 | P23: Didanosine EC 400mg [Videx EC], delayed-release capsules, Blister 3 x 10 Caps | Q23: Didanosine EC | R23: Videx EC | S23: 400mg | T23: Delayed-release capsules - blister | U23: 30 | V23: 50 | W23: 1183.5 | X23: 23.67 | Y23: 0.79 | Z23: 2 | AA23: 330 | AB23: 1 | AC23: 2008 | AE23: 39.5
B24: 3470 | C24: SCMS-32250 | D24: ASN-3001 | E24: Uganda | F24: ARV | G24: Adult | H24: BRISTOL-MYERS SQUIBB | I24: Direct Drop | J24: CIP | K24: Air | L24: 39738 | M24: 39791 | N24: 39791 | O24: 39791 | P24: Didanosine EC 250mg [Videx EC], delayed-release capsules, Blister 3 x 10 Caps | Q24: Didanosine EC | R24: Videx EC | S24: 250mg | T24: Delayed-release capsules - blister | U24: 30 | V24: 50 | W24: 917 | X24: 18.34 | Y24: 0.61 | Z24: 2 | AA24: 378 | AB24: 1 | AC24: 2008 | AE24: 30.5
B25: 3828 | C25: SCMS-43870 | D25: ASN-4687 | E25: Rwanda | F25: ARV | G25: Adult | H25: MYLAN LABORATORIES LTD (FORMERLY MATRIX LABORATORIES) | I25: Direct Drop | J25: CIP | K25: Air | L25: 39918 | M25: 40077 | N25: 40077 | O25: 40077 | P25: Lamivudine/Nevirapine/Zidovudine 150/200/300mg, tablets, 60 Tabs | Q25: Lamivudine/Nevirapine/Zidovudine | R25: Generic | S25: 150/300/200mg | T25: Tablet - FDC | U25: 60 | V25: 54432 | W25: 641753.28 | X25: 11.79 | Y25: 0.2 | Z25: 7278 | AA25: 61925.7 | AB25: 1 | AC25: 2009 | AE25: 10886.4
B26: 3955 | C26: SCMS-157 | D26: ASN-127 | E26: Uganda | F26: ARV | G26: Adult | H26: Aurobindo Pharma Limited | I26: Direct Drop | J26: EXW | K26: Air | M26: 39072 | N26: 39072 | O26: 39072 | P26: Lamivudine/Zidovudine 150/300mg, tablets, 60 Tabs | Q26: Lamivudine/Zidovudine | R26: Generic | S26: 150/300mg | T26: Tablet - FDC | U26: 60 | V26: 5080 | W26: 55880 | X26: 11 | Y26: 0.18 | Z26: 1172 | AA26: 5595.44 | AB26: 1 | AC26: 2006 | AE26: 914.4
B27: 4193 | C27: SCMS-14221 | D27: ASN-1595 | E27: Rwanda | F27: ARV | G27: Adult | H27: CIPLA LIMITED | I27: Direct Drop | J27: CIP | K27: Air | L27: 39407 | M27: 39566 | N27: 39560 | O27: 39560 | P27: Lamivudine/Nevirapine/Stavudine 150/200/30mg, tablets, 60 Tabs | Q27: Lamivudine/Nevirapine/Stavudine | R27: Generic | S27: 150/200/30mg | T27: Tablet - FDC | U27: 60 | V27: 38784 | W27: 271488 | X27: 7 | Y27: 0.12 | Z27: 4124 | AA27: 10500 | AB27: 1 | AC27: 2008 | AE27: 4654.08
B28: 4567 | C28: SCMS-23611 | D28: ASN-2727 | E28: Tanzania | F28: ARV | G28: Adult | H28: BRISTOL-MYERS SQUIBB | I28: Direct Drop | J28: CIP | K28: Air | L28: 39583 | M28: 39755 | N28: 39755 | O28: 39755 | P28: Didanosine EC 400mg [Videx EC], delayed-release capsules, Blister 3 x 10 Caps | Q28: Didanosine EC | R28: Videx EC | S28: 400mg | T28: Delayed-release capsules - blister | U28: 30 | V28: 2597 | W28: 61470.99 | X28: 23.67 | Y28: 0.79 | AB28: 1 | AC28: 2008 | AE28: 2051.63
B29: 4709 | C29: SCMS-30310 | D29: ASN-3505 | E29: Rwanda | F29: ARV | G29: Adult | H29: CIPLA LIMITED | I29: Direct Drop | J29: CIP | K29: Air | L29: 39742 | M29: 39882 | N29: 39882 | O29: 39882 | P29: Lamivudine/Zidovudine 150/300mg, tablets, 60 Tabs | Q29: Lamivudine/Zidovudine | R29: Generic | S29: 150/300mg | T29: Tablet - FDC | U29: 60 | V29: 18560 | W29: 168896 | X29: 9.1 | Y29: 0.15 | Z29: 1698 | AA29: 16414.22 | AB29: 1 | AC29: 2009 | AE29: 2784
B30: 4824 | C30: SCMS-34690 | D30: ASN-3853 | E30: Tanzania | F30: ARV | G30: Adult | H30: MERCK SHARP & DOHME IDEA GMBH (FORMALLY MERCK SHARP & DOHME B.V.) | I30: Direct Drop | J30: CIP | K30: Air | L30: 39812 | M30: 39979 | N30: 39979 | O30: 39979 | P30: Efavirenz/Emtricitabine/Tenofovir Disoproxil Fumarate 600/200/300mg [Atripla], tablets, 30 Tabs | Q30: Efavirenz/Emtricitabine/Tenofovir Disoproxil Fumarate | R30: Atripla | S30: 600/200/300mg | T30: Tablet - FDC | U30: 30 | V30: 24963 | W30: 1258135.2 | X30: 50.4 | Y30: 1.68 | Z30: 2462 | AA30: 3451.41 | AB30: 1 | AC30: 2009 | AE30: 41937.84
B31: 4949 | C31: SCMS-38410 | D31: ASN-4381 | E31: Tanzania | F31: ARV | G31: Adult | H31: ABBVIE LOGISTICS (FORMERLY ABBOTT LOGISTICS BV) | I31: Direct Drop | J31: FCA | K31: Air | L31: 39849 | M31: 40036 | N31: 40036 | O31: 40036 | P31: Lopinavir/Ritonavir 200/50mg [Aluvia], tablets, 120 Tabs | Q31: Lopinavir/Ritonavir | R31: Aluvia | S31: 200/50mg | T31: Tablet | U31: 120 | V31: 10680 | W31: 438948 | X31: 41.1 | Y31: 0.34 | Z31: 2724 | AA31: 12620.12 | AB31: 1 | AC31: 2009 | AE31: 3631.2
B32: 5113 | C32: SCMS-43900 | D32: ASN-4553 | E32: Rwanda | F32: ARV | G32: Adult | H32: HETERO LABS LIMITED | I32: Direct Drop | J32: CIP | K32: Air | L32: 40009 | M32: 40037 | N32: 40037 | O32: 40037 | P32: Efavirenz 600mg, tablets, 30 Tabs | Q32: Efavirenz | R32: Generic | S32: 600mg | T32: Tablet | U32: 30 | V32: 28034 | W32: 195677.32 | X32: 6.98 | Y32: 0.23 | Z32: 2268 | AA32: 19023.36 | AB32: 1 | AC32: 2009 | AE32: 6447.82
B33: 5175 | C33: SCMS-46500 | D33: ASN-4223 | E33: Tanzania | F33: ARV | G33: Adult | H33: Hoffmann-La Roche ltd Basel | I33: Direct Drop | J33: FCA | K33: Air | L33: 39961 | M33: 40024 | N33: 40024 | O33: 40024 | P33: Saquinavir 200mg [Invirase], capsules, 270 Caps | Q33: Saquinavir | R33: Invirase | S33: 200mg | T33: Capsule | U33: 270 | V33: 820 | W33: 73074.13 | X33: 89.11 | Y33: 0.33 | Z33: 424 | AA33: 3310.89 | AB33: 1 | AC33: 2009 | AE33: 270.6
B34: 5277 | C34: SCMS-159 | D34: ASN-125 | E34: Uganda | F34: ARV | G34: Adult | H34: SUN PHARMACEUTICAL INDUSTRIES LTD (RANBAXY LABORATORIES LIMITED) | I34: Direct Drop | J34: EXW | K34: Air | M34: 39073 | N34: 39073 | O34: 39073 | P34: Lamivudine 150mg, tablets, 60 Tabs | Q34: Lamivudine | R34: Generic | S34: 150mg | T34: Tablet | U34: 60 | V34: 6349 | W34: 21269.15 | X34: 3.35 | Y34: 0.06 | Z34: 369 | AA34: 2623.49 | AB34: 1 | AC34: 2006 | AE34: 380.94
B35: 5905 | C35: SCMS-26640 | D35: ASN-2408 | E35: Tanzania | F35: ARV | G35: Pediatric | H35: GLAXOSMITHKLINE EXPORT LIMITED | I35: Direct Drop | J35: CIP | K35: Air | L35: 39633 | M35: 39699 | N35: 39699 | O35: 39699 | P35: Abacavir 20mg/ml [Ziagen], oral solution, Bottle, 240 ml | Q35: Abacavir | R35: Ziagen | S35: 20mg/ml | T35: Oral solution | U35: 240 | V35: 132 | W35: 1990.56 | X35: 15.08 | Y35: 0.06 | Z35: 65 | AA35: 633 | AB35: 1 | AC35: 2008 | AE35: 7.92
B36: 6621 | C36: SCMS-157 | D36: ASN-127 | E36: Uganda | F36: ARV | G36: Adult | H36: Aurobindo Pharma Limited | I36: Direct Drop | J36: EXW | K36: Air | M36: 39072 | N36: 39072 | O36: 39072 | P36: Stavudine 30mg, capsules, 60 Caps | Q36: Stavudine | R36: Generic | S36: 30mg | T36: Capsule | U36: 60 | V36: 6349 | W36: 12380.55 | X36: 1.95 | Y36: 0.03 | AB36: 1 | AC36: 2006 | AE36: 190.47
B37: 6622 | C37: SCMS-160 | D37: ASN-124 | E37: Uganda | F37: ARV | G37: Adult | H37: STRIDES ARCOLAB LIMITED | I37: Direct Drop | J37: EXW | K37: Air | M37: 39084 | N37: 39084 | O37: 39084 | P37: Nevirapine 200mg, tablets, 60 Tabs | Q37: Nevirapine | R37: Generic | S37: 200mg | T37: Tablet | U37: 60 | V37: 6349 | W37: 21586.6 | X37: 3.4 | Y37: 0.06 | Z37: 355 | AA37: 3181.2 | AB37: 1 | AC37: 2007 | AE37: 380.94
B38: 6705 | C38: SCMS-800 | D38: ASN-719 | E38: Rwanda | F38: ARV | G38: Pediatric | H38: BRISTOL-MYERS SQUIBB | I38: Direct Drop | J38: CIP | K38: Air | L38: 39280 | M38: 39339 | N38: 39339 | O38: 39339 | P38: Didanosine 50mg [Videx], chewable tablets, 60 Tabs | Q38: Didanosine | R38: Videx | S38: 50mg | T38: Chewable/dispersible tablet | U38: 60 | V38: 182 | W38: 1729 | X38: 9.5 | Y38: 0.16 | Z38: 40 | AA38: 86.4 | AB38: 1 | AC38: 2007 | AE38: 29.12
B39: 6837 | C39: SCMS-13900 | D39: ASN-990 | E39: Rwanda | F39: ARV | G39: Adult | H39: ASPEN PHARMACARE | I39: Direct Drop | J39: EXW | K39: Air | L39: 39398 | M39: 39475 | N39: 39475 | O39: 39475 | P39: Tenofovir Disoproxil Fumarate 300mg [Viread], tablets, 30 Tabs | Q39: Tenofovir Disoproxil Fumarate | R39: Viread | S39: 300mg | T39: Tablet | U39: 30 | V39: 84 | W39: 0.84 | X39: 0.01 | Y39: 0 | AB39: 1 | AC39: 2008 | AE39: 0
B40: 6848 | C40: SCMS-14221 | D40: ASN-1594 | E40: Rwanda | F40: ARV | G40: Adult | H40: CIPLA LIMITED | I40: Direct Drop | J40: CIP | K40: Air | L40: 39407 | M40: 39566 | N40: 39560 | O40: 39560 | P40: Lamivudine/Nevirapine/Stavudine 150/200/30mg, tablets, 60 Tabs | Q40: Lamivudine/Nevirapine/Stavudine | R40: Generic | S40: 150/200/30mg | T40: Tablet - FDC | U40: 60 | V40: 34576 | W40: 242032 | X40: 7 | Y40: 0.12 | Z40: 3656 | AA40: 10500 | AB40: 1 | AC40: 2008 | AE40: 4149.12
B41: 6849 | C41: SCMS-14221 | D41: ASN-1596 | E41: Rwanda | F41: ARV | G41: Adult | H41: CIPLA LIMITED | I41: Direct Drop | J41: CIP | K41: Air | L41: 39407 | M41: 39566 | N41: 39566 | O41: 39566 | P41: Lamivudine/Nevirapine/Stavudine 150/200/30mg, tablets, 60 Tabs | Q41: Lamivudine/Nevirapine/Stavudine | R41: Generic | S41: 150/200/30mg | T41: Tablet - FDC | U41: 60 | V41: 16640 | W41: 116480 | X41: 7 | Y41: 0.12 | Z41: 1766 | AA41: 10500 | AB41: 1 | AC41: 2008 | AE41: 1996.8
B42: 6896 | C42: SCMS-16220 | D42: ASN-1329 | E42: Ethiopia | F42: ARV | G42: Adult | H42: ASPEN PHARMACARE | I42: Direct Drop | J42: EXW | K42: Air | L42: 39450 | M42: 39511 | N42: 39511 | O42: 39511 | P42: Tenofovir Disoproxil Fumarate 300mg [Viread], tablets, 30 Tabs | Q42: Tenofovir Disoproxil Fumarate | R42: Viread | S42: 300mg | T42: Tablet | U42: 30 | V42: 14820 | W42: 251940 | X42: 17 | Y42: 0.57 | Z42: 1233 | AA42: 5137.76 | AB42: 1 | AC42: 2008 | AE42: 8447.4
B43: 6931 | C43: SCMS-16760 | D43: ASN-1697 | E43: Tanzania | F43: ARV | G43: Pediatric | H43: GLAXOSMITHKLINE EXPORT LIMITED | I43: Direct Drop | J43: CIP | K43: Air | L43: 39471 | M43: 39576 | N43: 39576 | O43: 39576 | P43: Abacavir 20mg/ml [Ziagen], oral solution, Bottle, 240 ml | Q43: Abacavir | R43: Ziagen | S43: 20mg/ml | T43: Oral solution | U43: 240 | V43: 132 | W43: 3300 | X43: 25 | Y43: 0.1 | AB43: 1 | AC43: 2008 | AE43: 13.2
B44: 7201 | C44: SCMS-25530 | D44: ASN-2068 | E44: Rwanda | F44: ARV | G44: Adult | H44: Aurobindo Pharma Limited | I44: Direct Drop | J44: CIP | K44: Air | L44: 39612 | M44: 39651 | N44: 39651 | O44: 39651 | P44: Lamivudine/Zidovudine 150/300mg, tablets, 60 Tabs | Q44: Lamivudine/Zidovudine | R44: Generic | S44: 150/300mg | T44: Tablet - FDC | U44: 60 | V44: 45168 | W44: 414642.24 | X44: 9.18 | Y44: 0.15 | Z44: 3953 | AA44: 23071.26 | AB44: 1 | AC44: 2008 | AE44: 6775.2
B45: 7638 | C45: SCMS-38400 | D45: ASN-3694 | E45: Tanzania | F45: ARV | G45: Adult | H45: ABBVIE LOGISTICS (FORMERLY ABBOTT LOGISTICS BV) | I45: Direct Drop | J45: FCA | K45: Air | L45: 39849 | M45: 39960 | N45: 39960 | O45: 39960 | P45: Lopinavir/Ritonavir 200/50mg [Aluvia], tablets, 120 Tabs | Q45: Lopinavir/Ritonavir | R45: Aluvia | S45: 200/50mg | T45: Tablet | U45: 120 | V45: 12560 | W45: 516216 | X45: 41.1 | Y45: 0.34 | Z45: 3073 | AA45: 12815.42 | AB45: 1 | AC45: 2009 | AE45: 4270.4
B46: 7849 | C46: SCMS-45660 | D46: ASN-4378 | E46: Uganda | F46: ARV | G46: Adult | H46: BRISTOL-MYERS SQUIBB | I46: Direct Drop | J46: CIP | K46: Air | L46: 39944 | M46: 40000 | N46: 40000 | O46: 40000 | P46: Didanosine EC 250mg [Videx EC], delayed-release capsules, Blister 3 x 10 Caps | Q46: Didanosine EC | R46: Videx EC | S46: 250mg | T46: Delayed-release capsules - blister | U46: 30 | V46: 84 | W46: 1540.56 | X46: 18.34 | Y46: 0.61 | Z46: 4 | AA46: 390.81 | AB46: 1 | AC46: 2009 | AE46: 51.24
B47: 7868 | C47: SCMS-46510 | D47: ASN-4696 | E47: Tanzania | F47: ARV | G47: Adult | H47: Hoffmann-La Roche ltd Basel | I47: Direct Drop | J47: FCA | K47: Air | L47: 39961 | M47: 40081 | N47: 40081 | O47: 40081 | P47: Saquinavir 200mg [Invirase], capsules, 270 Caps | Q47: Saquinavir | R47: Invirase | S47: 200mg | T47: Capsule | U47: 270 | V47: 5178 | W47: 461436.41 | X47: 89.11 | Y47: 0.33 | Z47: 2666 | AA47: 16751.58 | AB47: 1 | AC47: 2009 | AE47: 1708.74
B48: 7975 | C48: SCMS-176 | D48: ASN-129 | E48: Uganda | F48: ARV | G48: Adult | H48: ASPEN PHARMACARE | I48: Direct Drop | J48: EXW | K48: Air | M48: 39073 | N48: 39073 | O48: 39073 | P48: Lamivudine/Zidovudine+Nevirapine 150/300+200mg, tablets, co-blister, 60+60 Tabs | Q48: Lamivudine/Zidovudine+Nevirapine | R48: Generic | S48: 150/300+200mg | T48: Tablet - FDC + co-blister | U48: 120 | V48: 1270 | W48: 26670 | X48: 21 | Y48: 0.18 | Z48: 201 | AA48: 1262.91 | AB48: 1 | AC48: 2006 | AE48: 228.6
B49: 8192 | C49: SCMS-14220 | D49: ASN-1305 | E49: Rwanda | F49: ARV | G49: Adult | H49: CIPLA LIMITED | I49: Direct Drop | J49: CIP | K49: Air | L49: 39407 | M49: 39566 | N49: 39518 | O49: 39518 | P49: Lamivudine/Nevirapine/Stavudine 150/200/30mg, tablets, 60 Tabs | Q49: Lamivudine/Nevirapine/Stavudine | R49: Generic | S49: 150/200/30mg | T49: Tablet - FDC | U49: 60 | V49: 100000 | W49: 700000 | X49: 7 | Y49: 0.12 | Z49: 10303 | AA49: 35034.75 | AB49: 1 | AC49: 2008 | AE49: 12000
B50: 8207 | C50: SCMS-14730 | D50: ASN-1066 | E50: Rwanda | F50: ARV | G50: Adult | H50: Aurobindo Pharma Limited | I50: Direct Drop | J50: CIP | K50: Air | L50: 39419 | M50: 39450 | N50: 39450 | O50: 39450 | P50: Efavirenz 600mg, tablets, 30 Tabs | Q50: Efavirenz | R50: Generic | S50: 600mg | T50: Tablet | U50: 30 | V50: 32510 | W50: 381992.5 | X50: 11.75 | Y50: 0.39 | Z50: 2791 | AA50: 28336.18 | AB50: 1 | AC50: 2008 | AE50: 12678.9
B51: 8218 | C51: SCMS-15220 | D51: ASN-1696 | E51: Tanzania | F51: ARV | G51: Pediatric | H51: BRISTOL-MYERS SQUIBB | I51: Direct Drop | J51: CIP | K51: Air | L51: 39426 | M51: 39576 | N51: 39576 | O51: 39576 | P51: Didanosine 2g [Videx], powder for oral solution 10mg/ml, reconstitute to 200 ml | Q51: Didanosine | R51: Videx | S51: 2g | T51: Powder for oral solution | U51: 200 | V51: 712 | W51: 8964.08 | X51: 12.59 | Y51: 0.06 | AB51: 1 | AC51: 2008 | AE51: 42.72
B52: 8803 | C52: SCMS-34690 | D52: ASN-3853 | E52: Tanzania | F52: ARV | G52: Adult | H52: MERCK SHARP & DOHME IDEA GMBH (FORMALLY MERCK SHARP & DOHME B.V.) | I52: Direct Drop | J52: CIP | K52: Air | L52: 39812 | M52: 39979 | N52: 39979 | O52: 39979 | P52: Efavirenz/Emtricitabine/Tenofovir Disoproxil Fumarate 600/200/300mg [Atripla], tablets, 30 Tabs | Q52: Efavirenz/Emtricitabine/Tenofovir Disoproxil Fumarate | R52: Atripla | S52: 600/200/300mg | T52: Tablet - FDC | U52: 30 | V52: 2680 | W52: 135072 | X52: 50.4 | Y52: 1.68 | AB52: 1 | AC52: 2009 | AE52: 4502.4
B53: 8864 | C53: SCMS-36490 | D53: ASN-3170 | E53: Tanzania | F53: ARV | G53: Adult | H53: ABBVIE LOGISTICS (FORMERLY ABBOTT LOGISTICS BV) | I53: Direct Drop | J53: FCA | K53: Air | L53: 39812 | M53: 39867 | N53: 39867 | O53: 39867 | P53: Lopinavir/Ritonavir 200/50mg [Aluvia], tablets, 120 Tabs | Q53: Lopinavir/Ritonavir | R53: Aluvia | S53: 200/50mg | T53: Tablet | U53: 120 | V53: 12500 | W53: 513750 | X53: 41.1 | Y53: 0.34 | Z53: 3088 | AA53: 12937.16 | AB53: 1 | AC53: 2009 | AE53: 4250
B54: 8922 | C54: SCMS-38410 | D54: ASN-4381 | E54: Tanzania | F54: ARV | G54: Adult | H54: ABBVIE LOGISTICS (FORMERLY ABBOTT LOGISTICS BV) | I54: Direct Drop | J54: FCA | K54: Air | L54: 39849 | M54: 40036 | N54: 40036 | O54: 40036 | P54: Lopinavir/Ritonavir 200/50mg [Aluvia], tablets, 120 Tabs | Q54: Lopinavir/Ritonavir | R54: Aluvia | S54: 200/50mg | T54: Tablet | U54: 120 | V54: 60 | W54: 2466 | X54: 41.1 | Y54: 0.34 | AB54: 1 | AC54: 2009 | AE54: 20.4
B55: 8989 | C55: SCMS-30311 | D55: ASN-3852 | E55: Rwanda | F55: ARV | G55: Adult | H55: CIPLA LIMITED | I55: Direct Drop | J55: CIP | K55: Air | L55: 39742 | M55: 39924 | N55: 39924 | O55: 39924 | P55: Lamivudine/Zidovudine 150/300mg, tablets, 60 Tabs | Q55: Lamivudine/Zidovudine | R55: Generic | S55: 150/300mg | T55: Tablet - FDC | U55: 60 | V55: 22752 | W55: 207043.2 | X55: 9.1 | Y55: 0.15 | Z55: 2086 | AA55: 853.87 | AB55: 1 | AC55: 2009 | AE55: 3412.8
B56: 9279 | C56: SCMS-157 | D56: ASN-127 | E56: Uganda | F56: ARV | G56: Adult | H56: Aurobindo Pharma Limited | I56: Direct Drop | J56: EXW | K56: Air | M56: 39072 | N56: 39072 | O56: 39072 | P56: Efavirenz 600mg, tablets, 30 Tabs | Q56: Efavirenz | R56: Generic | S56: 600mg | T56: Tablet | U56: 30 | V56: 5080 | W56: 85090 | X56: 16.75 | Y56: 0.56 | AB56: 1 | AC56: 2006 | AE56: 2844.8
B57: 9499 | C57: SCMS-14730 | D57: ASN-1067 | E57: Rwanda | F57: ARV | G57: Adult | H57: Aurobindo Pharma Limited | I57: Direct Drop | J57: CIP | K57: Air | L57: 39419 | M57: 39450 | N57: 39450 | O57: 39450 | P57: Efavirenz 600mg, tablets, 30 Tabs | Q57: Efavirenz | R57: Generic | S57: 600mg | T57: Tablet | U57: 30 | V57: 48259 | W57: 567043.25 | X57: 11.75 | Y57: 0.39 | Z57: 4143 | AA57: 19088.86 | AB57: 1 | AC57: 2008 | AE57: 18821.01
B58: 9550 | C58: SCMS-16220 | D58: ASN-1329 | E58: Ethiopia | F58: ARV | G58: Adult | H58: ASPEN PHARMACARE | I58: Direct Drop | J58: EXW | K58: Air | L58: 39450 | M58: 39511 | N58: 39511 | O58: 39511 | P58: Tenofovir Disoproxil Fumarate 300mg [Viread], tablets, 30 Tabs | Q58: Tenofovir Disoproxil Fumarate | R58: Viread | S58: 300mg | T58: Tablet | U58: 30 | V58: 780 | W58: 7.8 | X58: 0.01 | Y58: 0 | AB58: 1 | AC58: 2008 | AE58: 0
B59: 9836 | C59: SCMS-25910 | D59: ASN-2390 | E59: Rwanda | F59: ARV | G59: Adult | H59: HETERO LABS LIMITED | I59: Direct Drop | J59: CIP | K59: Air | L59: 39666 | M59: 39714 | N59: 39714 | O59: 39714 | P59: Efavirenz 600mg, tablets, 30 Tabs | Q59: Efavirenz | R59: Generic | S59: 600mg | T59: Tablet | U59: 30 | V59: 83400 | W59: 931578 | X59: 11.17 | Y59: 0.37 | Z59: 6701 | AA59: 87692.85 | AB59: 1 | AC59: 2008 | AE59: 30858
B60: 10126 | C60: SCMS-34690 | D60: ASN-3853 | E60: Tanzania | F60: ARV | G60: Adult | H60: MERCK SHARP & DOHME IDEA GMBH (FORMALLY MERCK SHARP & DOHME B.V.) | I60: Direct Drop | J60: CIP | K60: Air | L60: 39812 | M60: 39979 | N60: 39979 | O60: 39979 | P60: Efavirenz/Emtricitabine/Tenofovir Disoproxil Fumarate 600/200/300mg [Atripla], tablets, 30 Tabs | Q60: Efavirenz/Emtricitabine/Tenofovir Disoproxil Fumarate | R60: Atripla | S60: 600/200/300mg | T60: Tablet - FDC | U60: 30 | V60: 2357 | W60: 118792.8 | X60: 50.4 | Y60: 1.68 | AB60: 1 | AC60: 2009 | AE60: 3959.76
B61: 10416 | C61: SCMS-43790 | D61: ASN-4460 | E61: Rwanda | F61: ARV | G61: Adult | H61: MYLAN LABORATORIES LTD (FORMERLY MATRIX LABORATORIES) | I61: Direct Drop | J61: CIP | K61: Air | L61: 39918 | M61: 40070 | N61: 40070 | O61: 40070 | P61: Lamivudine/Zidovudine 150/300mg, tablets, 60 Tabs | Q61: Lamivudine/Zidovudine | R61: Generic | S61: 150/300mg | T61: Tablet - FDC | U61: 60 | V61: 38736 | W61: 348624 | X61: 9 | Y61: 0.15 | Z61: 3080 | AA61: 33235.44 | AB61: 1 | AC61: 2009 | AE61: 5810.4
B62: 10600 | C62: SO-1080 | D62: DN-362 | E62: Uganda | F62: ARV | G62: Adult | H62: SCMS from RDC | I62: From RDC | J62: N/A - From RDC | K62: Air | M62: 39391 | N62: 39391 | O62: 39391 | P62: Lamivudine/Nevirapine/Stavudine 150/200/30mg, tablets, 60 Tabs | Q62: Lamivudine/Nevirapine/Stavudine | R62: Generic | S62: 150/200/30mg | T62: Tablet - FDC | U62: 60 | V62: 1953 | W62: 14452.2 | X62: 7.4 | Y62: 0.12 | Z62: 283 | AA62: 1673 | AB62: 1 | AC62: 2007 | AE62: 234.36
B63: 10613 | C63: SO-914 | D63: DN-332 | E63: Ethiopia | F63: ARV | G63: Pediatric | H63: SCMS from RDC | I63: From RDC | J63: N/A - From RDC | K63: N/A | M63: 39329 | N63: 39329 | O63: 39329 | P63: Zidovudine 10mg/ml, oral solution, Bottle, 240 ml | Q63: Zidovudine | R63: Generic | S63: 10mg/ml | T63: Oral solution | U63: 240 | V63: 13850 | W63: 29777.5 | X63: 2.15 | Y63: 0.01 | Z63: 35216 | AA63: 88801 | AB63: 1 | AC63: 2007 | AE63: 138.5
B64: 10637 | C64: SO-1342 | D64: DN-459 | E64: Ethiopia | F64: ARV | G64: Pediatric | H64: SCMS from RDC | I64: From RDC | J64: N/A - From RDC | K64: Air | M64: 39412 | N64: 39412 | O64: 39412 | P64: Stavudine 1mg/ml, powder for oral solution, 200 ml | Q64: Stavudine | R64: Generic | S64: 1mg/ml | T64: Oral solution | U64: 200 | V64: 7294 | W64: 10211.6 | X64: 1.4 | Y64: 0.01 | Z64: 753 | AA64: 8004 | AB64: 1 | AC64: 2007 | AE64: 72.94
B65: 10662 | C65: SO-1647 | D65: DN-556 | E65: Tanzania | F65: ARV | G65: Adult | H65: SCMS from RDC | I65: From RDC | J65: N/A - From RDC | K65: Air | M65: 39484 | N65: 39484 | O65: 39484 | P65: Lamivudine/Zidovudine 150/300mg, tablets, 60 Tabs | Q65: Lamivudine/Zidovudine | R65: Generic | S65: 150/300mg | T65: Tablet - FDC | U65: 60 | V65: 9476 | W65: 90022 | X65: 9.5 | Y65: 0.16 | Z65: 1008 | AA65: 4207.4 | AB65: 1 | AC65: 2008 | AE65: 1516.16
B66: 10669 | C66: SO-1715 | D66: DN-588 | E66: Uganda | F66: ARV | G66: Adult | H66: SCMS from RDC | I66: From RDC | J66: N/A - From RDC | K66: N/A | M66: 39513 | N66: 39513 | O66: 39513 | P66: Emtricitabine/Tenofovir Disoproxil Fumarate 200/300mg [Truvada], tablets, 30 Tabs | Q66: Emtricitabine/Tenofovir Disoproxil Fumarate | R66: Truvada | S66: 300/200mg | T66: Tablet - FDC | U66: 30 | V66: 656 | W66: 17220 | X66: 26.25 | Y66: 0.88 | Z66: 58 | AA66: 794.22 | AB66: 1 | AC66: 2008 | AE66: 577.28
B67: 10670 | C67: SO-1082 | D67: DN-589 | E67: Uganda | F67: ARV | G67: Adult | H67: SCMS from RDC | I67: From RDC | J67: N/A - From RDC | K67: N/A | M67: 39506 | N67: 39506 | O67: 39506 | P67: Lamivudine/Nevirapine/Stavudine 150/200/30mg, tablets, 60 Tabs | Q67: Lamivudine/Nevirapine/Stavudine | R67: Generic | S67: 150/200/30mg | T67: Tablet - FDC | U67: 60 | V67: 93 | W67: 688.2 | X67: 7.4 | Y67: 0.12 | Z67: 311 | AA67: 1430.22 | AB67: 1 | AC67: 2008 | AE67: 11.16
B68: 10674 | C68: SO-2560 | D68: DN-826 | E68: Tanzania | F68: ARV | G68: Adult | H68: SCMS from RDC | I68: From RDC | J68: N/A - From RDC | K68: Air | M68: 39658 | N68: 39658 | O68: 39658 | P68: Nevirapine 200mg, tablets, 60 Tabs | Q68: Nevirapine | R68: Generic | S68: 200mg | T68: Tablet | U68: 60 | V68: 1300 | W68: 4420 | X68: 3.4 | Y68: 0.06 | Z68: 16709 | AA68: 15210 | AB68: 1 | AC68: 2008 | AE68: 78
B69: 10685 | C69: SO-1949 | D69: DN-668 | E69: Ethiopia | F69: ARV | G69: Adult | H69: SCMS from RDC | I69: From RDC | J69: N/A - From RDC | K69: N/A | M69: 39532 | N69: 39532 | O69: 39532 | P69: Stavudine 30mg, capsules, 60 Caps | Q69: Stavudine | R69: Generic | S69: 30mg | T69: Capsule | U69: 60 | V69: 51293 | W69: 77965.36 | X69: 1.52 | Y69: 0.03 | Z69: 3371 | AA69: 11862.2 | AB69: 1 | AC69: 2008 | AE69: 1538.79
B70: 10693 | C70: SO-1301 | D70: DN-480 | E70: Uganda | F70: ARV | G70: Adult | H70: SCMS from RDC | I70: From RDC | J70: N/A - From RDC | K70: Air | M70: 39526 | N70: 39526 | O70: 39526 | P70: Efavirenz 600mg, tablets, 30 Tabs | Q70: Efavirenz | R70: Generic | S70: 600mg | T70: Tablet | U70: 30 | V70: 2060 | W70: 25585.2 | X70: 12.42 | Y70: 0.41 | Z70: 196 | AA70: 1381.7 | AB70: 1 | AC70: 2008 | AE70: 844.6
B71: 10696 | C71: SO-2704 | D71: DN-799 | E71: Tanzania | F71: ARV | G71: Adult | H71: SCMS from RDC | I71: From RDC | J71: N/A - From RDC | K71: Air | M71: 39638 | N71: 39638 | O71: 39638 | P71: Abacavir 300mg, tablets, 60 Tabs | Q71: Abacavir | R71: Generic | S71: 300mg | T71: Tablet | U71: 60 | V71: 5730 | W71: 157746.9 | X71: 27.53 | Y71: 0.46 | Z71: 569 | AA71: 886.35 | AB71: 1 | AC71: 2008 | AE71: 2635.8
B72: 10708 | C72: SO-2720 | D72: DN-765 | E72: Tanzania | F72: ARV | G72: Adult | H72: SCMS from RDC | I72: From RDC | J72: N/A - From RDC | K72: Air | M72: 39630 | N72: 39630 | O72: 39630 | P72: Lamivudine 150mg, tablets, 60 Tabs | Q72: Lamivudine | R72: Generic | S72: 150mg | T72: Tablet | U72: 60 | V72: 23230 | W72: 67599.3 | X72: 2.91 | Y72: 0.05 | Z72: 1156 | AA72: 6308.6 | AB72: 1 | AC72: 2008 | AE72: 1161.5
B73: 10711 | C73: SO-17760 | D73: DN-1143 | E73: Uganda | F73: ARV | G73: Adult | H73: SCMS from RDC | I73: From RDC | J73: N/A - From RDC | K73: Air | M73: 39905 | N73: 39905 | O73: 39905 | P73: Lamivudine/Zidovudine 150/300mg, tablets, 60 Tabs | Q73: Lamivudine/Zidovudine | R73: Generic | S73: 150/300mg | T73: Tablet - FDC | U73: 60 | V73: 3505 | W73: 32771.75 | X73: 9.35 | Y73: 0.16 | Z73: 6556 | AA73: 5401.95 | AB73: 1 | AC73: 2009 | AE73: 560.8
... B95: 10863 | C95: SO-895 | D95: DN-298 | E95: Uganda | F95: ARV | G95: Adult | H95: SCMS from RDC | I95: From RDC | J95: N/A - From RDC | K95: Air | M95: 39321 | N95: 39321 | O95: 39321 | P95: Nevirapine 200mg, tablets, 60 Tabs | Q95: Nevirapine | R95: Generic | S95: 200mg | T95: Tablet | U95: 60 | V95: 1859 | W95: 6320.6 | X95: 3.4 | Y95: 0.06 | Z95: 214 | AA95: 891 | AB95: 1 | AC95: 2007 | AE95: 111.54
B96: 10878 | C96: SO-914 | D96: DN-332 | E96: Ethiopia | F96: ARV | G96: Pediatric | H96: SCMS from RDC | I96: From RDC | J96: N/A - From RDC | K96: N/A | M96: 39329 | N96: 39329 | O96: 39329 | P96: Zidovudine 10mg/ml, oral solution, Bottle, 240 ml | Q96: Zidovudine | R96: Generic | S96: 10mg/ml | T96: Oral solution | U96: 240 | V96: 13850 | W96: 29777.5 | X96: 2.15 | Y96: 0.01 | AB96: 1 | AC96: 2007 | AE96: 138.5
B97: 10879 | C97: SO-914 | D97: DN-332 | E97: Ethiopia | F97: ARV | G97: Pediatric | H97: SCMS from RDC | I97: From RDC | J97: N/A - From RDC | K97: N/A | M97: 39329 | N97: 39329 | O97: 39329 | P97: Lamivudine 10mg/ml, oral solution, Bottle, 240 ml | Q97: Lamivudine | R97: Generic | S97: 10mg/ml | T97: Oral solution | U97: 240 | V97: 15913 | W97: 31348.61 | X97: 1.97 | Y97: 0.01 | AB97: 1 | AC97: 2007 | AE97: 159.13
B98: 10880 | C98: SO-914 | D98: DN-332 | E98: Ethiopia | F98: ARV | G98: Adult | H98: SCMS from RDC | I98: From RDC | J98: N/A - From RDC | K98: N/A | M98: 39329 | N98: 39329 | O98: 39329 | P98: Stavudine 30mg, capsules, 60 Caps | Q98: Stavudine | R98: Generic | S98: 30mg | T98: Capsule | U98: 60 | V98: 14700 | W98: 22344 | X98: 1.52 | Y98: 0.03 | AB98: 1 | AC98: 2007 | AE98: 441
B99: 10889 | C99: SO-1123 | D99: DN-381 | E99: Uganda | F99: ARV | G99: Adult | H99: SCMS from RDC | I99: From RDC | J99: N/A - From RDC | K99: Air | M99: 39391 | N99: 39391 | O99: 39391 | P99: Efavirenz 600mg, tablets, 30 Tabs | Q99: Efavirenz | R99: Generic | S99: 600mg | T99: Tablet | U99: 30 | V99: 1717 | W99: 21325.14 | X99: 12.42 | Y99: 0.41 | Z99: 151 | AA99: 1157.58 | AB99: 1 | AC99: 2007 | AE99: 703.97
B100: 10906 | C100: SO-1085 | D100: DN-430 | E100: Uganda | F100: ARV | G100: Adult | H100: SCMS from RDC | I100: From RDC | J100: N/A - From RDC | K100: Air | M100: 39426 | N100: 39426 | O100: 39426 | P100: Lamivudine/Nevirapine/Zidovudine 150/200/300mg, tablets, 60 Tabs | Q100: Lamivudine/Nevirapine/Zidovudine | R100: Generic | S100: 150/300/200mg | T100: Tablet - FDC | U100: 60 | V100: 1650 | W100: 22275 | X100: 13.5 | Y100: 0.22 | Z100: 197 | AA100: 1637 | AB100: 1 | AC100: 2007 | AE100: 363
B101: 10908 | C101: SO-1300 | D101: DN-435 | E101: Uganda | F101: ARV | G101: Adult | H101: SCMS from RDC | I101: From RDC | J101: N/A - From RDC | K101: Air | M101: 39426 | N101: 39426 | O101: 39426 | P101: Emtricitabine/Tenofovir Disoproxil Fumarate 200/300mg [Truvada], tablets, 30 Tabs | Q101: Emtricitabine/Tenofovir Disoproxil Fumarate | R101: Truvada | S101: 300/200mg | T101: Tablet - FDC | U101: 30 | V101: 42 | W101: 1102.5 | X101: 26.25 | Y101: 0.88 | Z101: 464 | AA101: 3393 | AB101: 1 | AC101: 2007 | AE101: 36.96
B102: 10917 | C102: SO-1527 | D102: DN-522 | E102: Ethiopia | F102: ARV | G102: Adult | H102: SCMS from RDC | I102: From RDC | J102: N/A - From RDC | K102: Air | M102: 39498 | N102: 39498 | O102: 39498 | P102: Stavudine 20mg, capsules, 60 Caps | Q102: Stavudine | R102: Generic | S102: 20mg | T102: Capsule | U102: 60 | V102: 219 | W102: 383.25 | X102: 1.75 | Y102: 0.03 | Z102: 16 | AA102: 472.5 | AB102: 1 | AC102: 2008 | AE102: 6.57
B103: 10918 | C103: SO-1514 | D103: DN-518 | E103: Ethiopia | F103: ARV | G103: Adult | H103: SCMS from RDC | I103: From RDC | J103: N/A - From RDC | K103: Air | M103: 39436 | N103: 39436 | O103: 39436 | P103: Tenofovir Disoproxil Fumarate 300mg [Viread], tablets, 30 Tabs | Q103: Tenofovir Disoproxil Fumarate | R103: Viread | S103: 300mg | T103: Tablet | U103: 30 | V103: 1184 | W103: 20128 | X103: 17 | Y103: 0.57 | Z103: 49 | AA103: 639.75 | AB103: 1 | AC103: 2007 | AE103: 674.88
B104: 10923 | C104: SO-1533 | D104: DN-528 | E104: Ethiopia | F104: ARV | G104: Pediatric | H104: SCMS from RDC | I104: From RDC | J104: N/A - From RDC | K104: Air | M104: 39436 | N104: 39436 | O104: 39436 | P104: Zidovudine 10mg/ml, oral solution, Bottle, 240 ml | Q104: Zidovudine | R104: Generic | S104: 10mg/ml | T104: Oral solution | U104: 240 | V104: 1926 | W104: 4140.9 | X104: 2.15 | Y104: 0.01 | Z104: 807 | AA104: 2511.67 | AB104: 1 | AC104: 2007 | AE104: 19.26
B105: 10929 | C105: SO-1525 | D105: DN-530 | E105: Ethiopia | F105: ARV | G105: Pediatric | H105: SCMS from RDC | I105: From RDC | J105: N/A - From RDC | K105: Air | M105: 39433 | N105: 39433 | O105: 39433 | P105: Efavirenz 200mg [Stocrin/Sustiva], capsule, 90 Caps | Q105: Efavirenz | R105: Stocrin/Sustiva | S105: 200mg | T105: Capsule | U105: 90 | V105: 1692 | W105: 27072 | X105: 16 | Y105: 0.18 | Z105: 182 | AA105: 1722 | AB105: 1 | AC105: 2007 | AE105: 304.56
B106: 10931 | C106: SO-1513 | D106: DN-516 | E106: Ethiopia | F106: ARV | G106: Adult | H106: SCMS from RDC | I106: From RDC | J106: N/A - From RDC | K106: Air | M106: 39457 | N106: 39457 | O106: 39457 | P106: Tenofovir Disoproxil Fumarate 300mg [Viread], tablets, 30 Tabs | Q106: Tenofovir Disoproxil Fumarate | R106: Viread | S106: 300mg | T106: Tablet | U106: 30 | V106: 591 | W106: 10047 | X106: 17 | Y106: 0.57 | Z106: 37 | AA106: 504 | AB106: 1 | AC106: 2008 | AE106: 336.87
B107: 10933 | C107: SO-1515 | D107: DN-570 | E107: Rwanda | F107: ARV | G107: Adult | H107: SCMS from RDC | I107: From RDC | J107: N/A - From RDC | K107: Air | M107: 39475 | N107: 39475 | O107: 39475 | P107: Lamivudine 150mg, tablets, 60 Tabs | Q107: Lamivudine | R107: Generic | S107: 150mg | T107: Tablet | U107: 60 | V107: 3150 | W107: 9576 | X107: 3.04 | Y107: 0.05 | Z107: 165 | AA107: 2559.28 | AB107: 1 | AC107: 2008 | AE107: 157.5
B108: 10936 | C108: SO-1532 | D108: DN-574 | E108: Ethiopia | F108: ARV | G108: Adult | H108: SCMS from RDC | I108: From RDC | J108: N/A - From RDC | K108: Air | M108: 39478 | N108: 39478 | O108: 39478 | P108: Nevirapine 200mg, tablets, 60 Tabs | Q108: Nevirapine | R108: Generic | S108: 200mg | T108: Tablet | U108: 60 | V108: 7511 | W108: 25537.4 | X108: 3.4 | Y108: 0.06 | Z108: 732 | AA108: 2724.27 | AB108: 1 | AC108: 2008 | AE108: 450.66
B109: 10940 | C109: SO-1648 | D109: DN-559 | E109: Tanzania | F109: ARV | G109: Pediatric | H109: SCMS from RDC | I109: From RDC | J109: N/A - From RDC | K109: Air | M109: 39503 | N109: 39503 | O109: 39503 | P109: Didanosine 100mg, chewable/dispersible tablets, 60 Tabs | Q109: Didanosine | R109: Generic | S109: 100mg | T109: Chewable/dispersible tablet | U109: 60 | V109: 2273 | W109: 17615.75 | X109: 7.75 | Y109: 0.13 | Z109: 2749 | AA109: 10654.94 | AB109: 1 | AC109: 2008 | AE109: 295.49
B110: 10943 | C110: SO-1719 | D110: DN-593 | E110: Ethiopia | F110: ARV | G110: Adult | H110: SCMS from RDC | I110: From RDC | J110: N/A - From RDC | K110: Air | M110: 39483 | N110: 39483 | O110: 39483 | P110: Zidovudine 300mg, tablets, 60 Tabs | Q110: Zidovudine | R110: Generic | S110: 300mg | T110: Tablet | U110: 60 | V110: 10000 | W110: 81500 | X110: 8.15 | Y110: 0.14 | Z110: 574 | AA110: 3787.32 | AB110: 1 | AC110: 2008 | AE110: 1400
... B112: 10949 | C112: SO-2000 | D112: DN-722 | E112: Tanzania | F112: ARV | G112: Adult | H112: SCMS from RDC | I112: From RDC | J112: N/A - From RDC | K112: N/A | M112: 39568 | N112: 39568 | O112: 39568 | P112: Lopinavir/Ritonavir 200/50mg [Aluvia], tablets, 120 Tabs | Q112: Lopinavir/Ritonavir | R112: Aluvia | S112: 200/50mg | T112: Tablet | U112: 120 | V112: 2580 | W112: 106038 | X112: 41.1 | Y112: 0.34 | Z112: 559 | AA112: 3562.4 | AB112: 1 | AC112: 2008 | AE112: 877.2
B113: 10950 | C113: SO-2560 | D113: DN-826 | E113: Tanzania | F113: ARV | G113: Adult | H113: SCMS from RDC | I113: From RDC | J113: N/A - From RDC | K113: Air | M113: 39658 | N113: 39658 | O113: 39658 | P113: Nevirapine 200mg, tablets, 60 Tabs | Q113: Nevirapine | R113: Generic | S113: 200mg | T113: Tablet | U113: 60 | V113: 50288 | W113: 170979.2 | X113: 3.4 | Y113: 0.06 | AB113: 1 | AC113: 2008 | AE113: 3017.28
B114: 10960 | C114: SO-1695 | D114: DN-663 | E114: Tanzania | F114: ARV | G114: Adult | H114: SCMS from RDC | I114: From RDC | J114: N/A - From RDC | K114: N/A | M114: 39560 | N114: 39561 | O114: 39561 | P114: Lamivudine/Zidovudine 150/300mg, tablets, 60 Tabs | Q114: Lamivudine/Zidovudine | R114: Generic | S114: 150/300mg | T114: Tablet - FDC | U114: 60 | V114: 51364 | W114: 487958 | X114: 9.5 | Y114: 0.16 | Z114: 5372 | AA114: 16430.72 | AB114: 0 | AC114: 2008 | AE114: 8218.24
B115: 10964 | C115: SO-2791 | D115: DN-794 | E115: Uganda | F115: ARV | G115: Pediatric | H115: SCMS from RDC | I115: From RDC | J115: N/A - From RDC | K115: Air | M115: 39640 | N115: 39640 | O115: 39640 | P115: Zidovudine 10mg/ml, oral solution, Bottle, 240 ml | Q115: Zidovudine | R115: Generic | S115: 10mg/ml | T115: Oral solution | U115: 240 | V115: 4296 | W115: 9021.6 | X115: 2.1 | Y115: 0.01 | Z115: 1600 | AA115: 10314.28 | AB115: 1 | AC115: 2008 | AE115: 42.96
B116: 10966 | C116: SO-2674 | D116: DN-797 | E116: Uganda | F116: ARV | G116: Adult | H116: SCMS from RDC | I116: From RDC | J116: N/A - From RDC | K116: Air | M116: 39640 | N116: 39640 | O116: 39640 | P116: Nevirapine 200mg, tablets, 60 Tabs | Q116: Nevirapine | R116: Generic | S116: 200mg | T116: Tablet | U116: 60 | V116: 1061 | W116: 3607.4 | X116: 3.4 | Y116: 0.06 | Z116: 106 | AA116: 1054.52 | AB116: 1 | AC116: 2008 | AE116: 63.66
B117: 10972 | C117: SO-1518 | D117: DN-634 | E117: Ethiopia | F117: ARV | G117: Adult | H117: SCMS from RDC | I117: From RDC | J117: N/A - From RDC | K117: Air | M117: 39528 | N117: 39528 | O117: 39528 | P117: Lamivudine/Zidovudine 150/300mg, tablets, 60 Tabs | Q117: Lamivudine/Zidovudine | R117: Generic | S117: 150/300mg | T117: Tablet - FDC | U117: 60 | V117: 65524 | W117: 622478 | X117: 9.5 | Y117: 0.16 | Z117: 14599 | AA117: 32146.52 | AB117: 1 | AC117: 2008 | AE117: 10483.84
B118: 10982 | C118: SO-1696 | D118: DN-763 | E118: Tanzania | F118: ARV | G118: Pediatric | H118: SCMS from RDC | I118: From RDC | J118: N/A - From RDC | K118: Air | M118: 39638 | N118: 39638 | O118: 39638 | P118: Didanosine 100mg, chewable/dispersible tablets, 60 Tabs | Q118: Didanosine | R118: Generic | S118: 100mg | T118: Chewable/dispersible tablet | U118: 60 | V118: 11640 | W118: 90210 | X118: 7.75 | Y118: 0.13 | Z118: 16778 | AA118: 9043.65 | AB118: 1 | AC118: 2008 | AE118: 1513.2
B119: 10986 | C119: SO-13190 | D119: DN-922 | E119: Tanzania | F119: ARV | G119: Adult | H119: SCMS from RDC | I119: From RDC | J119: N/A - From RDC | K119: Air | M119: 39742 | N119: 39742 | O119: 39742 | P119: Lamivudine/Nevirapine/Stavudine 150/200/30mg, tablets, 60 Tabs | Q119: Lamivudine/Nevirapine/Stavudine | R119: Generic | S119: 150/200/30mg | T119: Tablet - FDC | U119: 60 | V119: 90323 | W119: 668390.2 | X119: 7.4 | Y119: 0.12 | Z119: 9635 | AA119: 52979.7 | AB119: 1 | AC119: 2008 | AE119: 10838.76
B120: 10995 | C120: SO-17720 | D120: DN-1043 | E120: Uganda | F120: ARV | G120: Adult | H120: SCMS from RDC | I120: From RDC | J120: N/A - From RDC | K120: Air | M120: 39848 | N120: 39848 | O120: 39848 | P120: Lamivudine/Nevirapine/Zidovudine 150/200/300mg, tablets, 60 Tabs | Q120: Lamivudine/Nevirapine/Zidovudine | R120: Generic | S120: 150/300/200mg | T120: Tablet - FDC | U120: 60 | V120: 20000 | W120: 236000 | X120: 11.8 | Y120: 0.2 | Z120: 2283 | AA120: 13586.1 | AB120: 1 | AC120: 2009 | AE120: 4000
B121: 10999 | C121: SO-2566 | D121: DN-891 | E121: Tanzania | F121: ARV | G121: Adult | H121: SCMS from RDC | I121: From RDC | J121: N/A - From RDC | K121: Truck | M121: 39714 | N121: 39714 | O121: 39714 | P121: Lamivudine/Nevirapine/Stavudine 150/200/30mg, tablets, 60 Tabs | Q121: Lamivudine/Nevirapine/Stavudine | R121: Generic | S121: 150/200/30mg | T121: Tablet - FDC | U121: 60 | V121: 123317 | W121: 912545.8 | X121: 7.4 | Y121: 0.12 | Z121: 13253 | AA121: 64506.78 | AB121: 1 | AC121: 2008 | AE121: 14798.04
B122: 11000 | C122: SO-17890 | D122: DN-1092 | E122: Uganda | F122: ARV | G122: Adult | H122: SCMS from RDC | I122: From RDC | J122: N/A - From RDC | K122: Air | M122: 39891 | N122: 39891 | O122: 39891 | P122: Lamivudine/Nevirapine/Zidovudine 150/200/300mg, tablets, 60 Tabs | Q122: Lamivudine/Nevirapine/Zidovudine | R122: Generic | S122: 150/300/200mg | T122: Tablet - FDC | U122: 60 | V122: 1893 | W122: 22337.4 | X122: 11.8 | Y122: 0.2 | Z122: 215 | AA122: 2408.91 | AB122: 1 | AC122: 2009 | AE122: 378.6
B123: 11001 | C123: SO-17830 | D123: DN-990 | E123: Uganda | F123: ARV | G123: Adult | H123: SCMS from RDC | I123: From RDC | J123: N/A - From RDC | K123: Air | M123: 39791 | N123: 39791 | O123: 39791 | P123: Lopinavir/Ritonavir 200/50mg [Aluvia], tablets, 120 Tabs | Q123: Lopinavir/Ritonavir | R123: Aluvia | S123: 200/50mg | T123: Tablet | U123: 120 | V123: 42 | W123: 1726.2 | X123: 41.1 | Y123: 0.34 | Z123: 123 | AA123: 845.37 | AB123: 1 | AC123: 2008 | AE123: 14.28
...

Sheet Calculation
N1: 2.2 On-time Delivery Rate (OTD%)
B2: 1. ARV value by Region and Supply method | F2: Commodity Value | G2: =SUM(tblARV[Line Item Value]) -> 2.8264668e+08 | Q2: 2.4 Comparative Delivery Reliability | X2: 2. Reasonable Procurement Cost
N3: Total Delivery | O3: =COUNTA($F$20:$F$1349) -> 1330 | Q3: 2.4.1 by Country
B4: Sum of Line Items | G4: Commodity Value by Fulfillment Chanel | N4: Count of On-time | O4: =COUNTIF($F$20:$F$1349,"On-time") -> 1156 | Y4: Item Description | Z4: Lamivudine/Nevirapine/Zidovudine 150/200/300mg, tablets, 60 Tabs
B5: 'Country | C5: Direct Drop | D5: From RDC | E5: Total | G5: Direct Drop | H5: =+C13 -> 84170273 | N5: Count of Late | O5: =COUNTIF($F$20:$F$1349,"Late") -> 174 | Q5: Row Labels | R5: Count of ASN/DN # | S5: Sum of On_time_flag | T5: Count of On_time_flag2
B6: Burundi | D6: 1271711 | E6: 1271711 | G6: From RDC | H6: =+D13 -> 1.9847641e+08 | N6: OTD Rate | O6: =O4/$O$3 -> 0.86917293 | Q6: Burundi | R6: 72 | S6: 34 | T6: 72 | Y6: Year | Z6: USD Per Pack
B7: Ethiopia | C7: 2939836.8 | D7: 10663658 | E7: 13603494 | G7: Total | H7: =SUM(H5:H6) -> 2.8264668e+08 | N7: OTD Rate Chanel | Q7: Ethiopia | R7: 141 | S7: 129 | T7: 141 | Y7: 2007 | Z7: 18.430108
B8: Kenya | D8: 7878.7 | E8: 7878.7 | N8: From RDC | O8: =COUNTIFS($F$20:$F$1349,"On-time",$H$20:$H$1349,$N8)/COUNTIF($H$20:$H$1349,$N8) -> 0.81950673 | Q8: Kenya | R8: 4 | S8: 4 | T8: 4 | Y8: 2008 | Z8: 11.996223
B9: Rwanda | C9: 35811698 | D9: 26324471 | E9: 62136169 | N9: Direct Drop | O9: =COUNTIFS($F$20:$F$1349,"On-time",$H$20:$H$1349,$N9)/COUNTIF($H$20:$H$1349,$N9) -> 0.97031963 | Q9: Rwanda | R9: 349 | S9: 315 | T9: 349 | Y9: 2009 | Z9: 11.578117
B10: Tanzania | C10: 30408879 | D10: 84151677 | E10: 1.1456056e+08 | Q10: South Sudan | R10: 52 | S10: 42 | T10: 52 | Y10: 2010 | Z10: 11.238156
B11: Uganda | C11: 15004699 | D11: 74857939 | E11: 89862638 | N11: 2.3 Average Delay Severity and Consistency | Q11: Tanzania | R11: 397 | S11: 336 | T11: 397 | Y11: 2011 | Z11: 11.203822
B12: South Sudan | C12: 5160.25 | D12: 1199076.5 | E12: 1204236.7 | N12: Average Delay | O12: =AVERAGEIF($E$20:$E$1349,">0") -> 21.488506 | Q12: Uganda | R12: 738 | S12: 641 | T12: 738 | Y12: 2012 | Z12: 10.477873
B13: Total | C13: 84170273 | D13: 1.9847641e+08 | E13: 2.8264668e+08 | N13: Max Delay | O13: =_xlfn.MAXIFS($E$20:$E$1349,$E$20:$E$1349,">0") -> 280 | Q13: Grand Total | R13: 1753 | S13: 1501 | T13: 1753 | Y13: 2013 | Z13: 8.3026637
N14: Min Delay | O14: =_xlfn.MINIFS($E$20:$E$1349,$E$20:$E$1349,">0") -> 1 | Y14: 2014 | Z14: 8.1930147
N15: Median Delay | O15: {=MEDIAN(_xlfn._xlws.FILTER(E$20:$E$1349,(E$20:$E$1349)>0))} -> 12 | Y15: 2015 | Z15: 7.9930262
B16: 2. ARV Delivery Reliability and Consistency | N16: STD.V Delpay | O16: {=_xlfn.STDEV.S(_xlfn._xlws.FILTER(E$20:$E$1349,(E$20:$E$1349)>0))} -> 30.303997 | Y16: Grand Total | Z16: 9.5359766
B18: 2.1 Delivery Variance | N18: 2.4 Comparative Delivery Reliability
B19: Delivery | C19: Scheduled date | D19: Actual Date | E19: Variance | F19: Delivery Status | G19: Country | H19: Fulfill Via | I19: Vendor | N19: 2.4.1 by Country | Q19: 1 | R19: {=INDEX(S19:S21,Q19)} -> All | S19: All
B20: ASN-10070 | C20: 40660 | D20: 40660 | E20: 0 | F20: =IF($E20<=0,"On-time","Late") -> On-time | G20: =_xlfn.XLOOKUP($B20,tblARV[ASN/DN '#],tblARV[Country],"Not found") -> Rwanda | H20: =_xlfn.XLOOKUP($B20,tblARV[ASN/DN '#],tblARV[Fulfill Via],"Not found") -> Direct Drop | I20: =_xlfn.XLOOKUP($B20,tblARV[ASN/DN '#],tblARV[Vendor],"Not found") -> MYLAN LABORATORIES LTD (FORMERLY MATRIX LABORATORIES) | S20: {=_xlfn.UNIQUE(tblARV[Fulfill Via])} -> Direct Drop
B21: ASN-10140 | C21: 40641 | D21: 40641 | E21: 0 | F21: =IF($E21<=0,"On-time","Late") -> On-time | G21: =_xlfn.XLOOKUP(B21,tblARV[ASN/DN '#],tblARV[Country],"Not found") -> Rwanda | H21: =_xlfn.XLOOKUP($B21,tblARV[ASN/DN '#],tblARV[Fulfill Via],"Not found") -> Direct Drop | I21: =_xlfn.XLOOKUP($B21,tblARV[ASN/DN '#],tblARV[Vendor],"Not found") -> Aurobindo Pharma Limited | S21: From RDC
B22: ASN-10317 | C22: 40694 | D22: 40694 | E22: 0 | F22: =IF($E22<=0,"On-time","Late") -> On-time | G22: =_xlfn.XLOOKUP(B22,tblARV[ASN/DN '#],tblARV[Country],"Not found") -> Rwanda | H22: =_xlfn.XLOOKUP($B22,tblARV[ASN/DN '#],tblARV[Fulfill Via],"Not found") -> Direct Drop | I22: =_xlfn.XLOOKUP($B22,tblARV[ASN/DN '#],tblARV[Vendor],"Not found") -> HETERO LABS LIMITED
B23: ASN-10338 | C23: 40631 | D23: 40631 | E23: 0 | F23: =IF($E23<=0,"On-time","Late") -> On-time | G23: =_xlfn.XLOOKUP(B23,tblARV[ASN/DN '#],tblARV[Country],"Not found") -> Uganda | H23: =_xlfn.XLOOKUP($B23,tblARV[ASN/DN '#],tblARV[Fulfill Via],"Not found") -> Direct Drop | I23: =_xlfn.XLOOKUP($B23,tblARV[ASN/DN '#],tblARV[Vendor],"Not found") -> ASPEN PHARMACARE
B24: ASN-1039 | C24: 39406 | D24: 39440 | E24: 34 | F24: =IF($E24<=0,"On-time","Late") -> Late | G24: =_xlfn.XLOOKUP(B24,tblARV[ASN/DN '#],tblARV[Country],"Not found") -> Ethiopia | H24: =_xlfn.XLOOKUP($B24,tblARV[ASN/DN '#],tblARV[Fulfill Via],"Not found") -> Direct Drop | I24: =_xlfn.XLOOKUP($B24,tblARV[ASN/DN '#],tblARV[Vendor],"Not found") -> Aurobindo Pharma Limited | N24: Country | O24: On-time | P24: Late | Q24: Total | R24: OTD% | S24: LTD%
B25: ASN-10455 | C25: 40652 | D25: 40652 | E25: 0 | F25: =IF($E25<=0,"On-time","Late") -> On-time | G25: =_xlfn.XLOOKUP(B25,tblARV[ASN/DN '#],tblARV[Country],"Not found") -> Uganda | H25: =_xlfn.XLOOKUP($B25,tblARV[ASN/DN '#],tblARV[Fulfill Via],"Not found") -> Direct Drop | I25: =_xlfn.XLOOKUP($B25,tblARV[ASN/DN '#],tblARV[Vendor],"Not found") -> MERCK SHARP & DOHME IDEA GMBH (FORMALLY MERCK SHARP & DOHME B.V.) | N25: Uganda | O25: =COUNTIFS($F$20:$F$1349,$O$24,$G$20:$G$1349,$N25) -> 477 | P25: =CHOOSE($Q$19,COUNTIFS($F$20:$F$1349,P$24,$G$20:$G$1349,$N25), COUNTIFS($F$20:$F$1349,P$24,$G$20:$G$1349,$N25,$H$20:$H$1349,$R$19), COUNTIFS($F$20:$F$1349,P$24,$G$20:$G$1349,$N25,$H$20:$H$1349,$R$19)) -> 68 | Q25: =SUM(O25:P25) -> 545 | R25: =+O25/Q25 -> 0.87522936 | S25: =P25/Q25 -> 0.12477064
B26: ASN-1066 | C26: 39450 | D26: 39450 | E26: 0 | F26: =IF($E26<=0,"On-time","Late") -> On-time | G26: =_xlfn.XLOOKUP(B26,tblARV[ASN/DN '#],tblARV[Country],"Not found") -> Rwanda | H26: =_xlfn.XLOOKUP($B26,tblARV[ASN/DN '#],tblARV[Fulfill Via],"Not found") -> Direct Drop | I26: =_xlfn.XLOOKUP($B26,tblARV[ASN/DN '#],tblARV[Vendor],"Not found") -> Aurobindo Pharma Limited | N26: Tanzania | O26: =COUNTIFS($F$20:$F$1349,$O$24,$G$20:$G$1349,$N26) -> 268 | P26: =CHOOSE($Q$19,COUNTIFS($F$20:$F$1349,P$24,$G$20:$G$1349,$N26), COUNTIFS($F$20:$F$1349,P$24,$G$20:$G$1349,$N26,$H$20:$H$1349,$R$19), COUNTIFS($F$20:$F$1349,P$24,$G$20:$G$1349,$N26,$H$20:$H$1349,$R$19)) -> 45 | Q26: =SUM(O26:P26) -> 313 | R26: =+O26/Q26 -> 0.85623003 | S26: =P26/Q26 -> 0.14376997
B27: ASN-10663 | C27: 40658 | D27: 40658 | E27: 0 | F27: =IF($E27<=0,"On-time","Late") -> On-time | G27: =_xlfn.XLOOKUP(B27,tblARV[ASN/DN '#],tblARV[Country],"Not found") -> Rwanda | H27: =_xlfn.XLOOKUP($B27,tblARV[ASN/DN '#],tblARV[Fulfill Via],"Not found") -> Direct Drop | I27: =_xlfn.XLOOKUP($B27,tblARV[ASN/DN '#],tblARV[Vendor],"Not found") -> Aurobindo Pharma Limited | N27: South Sudan | O27: =COUNTIFS($F$20:$F$1349,$O$24,$G$20:$G$1349,$N27) -> 19 | P27: =CHOOSE($Q$19,COUNTIFS($F$20:$F$1349,P$24,$G$20:$G$1349,$N27), COUNTIFS($F$20:$F$1349,P$24,$G$20:$G$1349,$N27,$H$20:$H$1349,$R$19), COUNTIFS($F$20:$F$1349,P$24,$G$20:$G$1349,$N27,$H$20:$H$1349,$R$19)) -> 5 | Q27: =SUM(O27:P27) -> 24 | R27: =+O27/Q27 -> 0.79166667 | S27: =P27/Q27 -> 0.20833333
B28: ASN-10666 | C28: 40667 | D28: 40667 | E28: 0 | F28: =IF($E28<=0,"On-time","Late") -> On-time | G28: =_xlfn.XLOOKUP(B28,tblARV[ASN/DN '#],tblARV[Country],"Not found") -> Ethiopia | H28: =_xlfn.XLOOKUP($B28,tblARV[ASN/DN '#],tblARV[Fulfill Via],"Not found") -> Direct Drop | I28: =_xlfn.XLOOKUP($B28,tblARV[ASN/DN '#],tblARV[Vendor],"Not found") -> Aurobindo Pharma Limited | N28: Rwanda | O28: =COUNTIFS($F$20:$F$1349,$O$24,$G$20:$G$1349,$N28) -> 276 | P28: =CHOOSE($Q$19,COUNTIFS($F$20:$F$1349,P$24,$G$20:$G$1349,$N28), COUNTIFS($F$20:$F$1349,P$24,$G$20:$G$1349,$N28,$H$20:$H$1349,$R$19), COUNTIFS($F$20:$F$1349,P$24,$G$20:$G$1349,$N28,$H$20:$H$1349,$R$19)) -> 27 | Q28: =SUM(O28:P28) -> 303 | R28: =+O28/Q28 -> 0.91089109 | S28: =P28/Q28 -> 0.089108911
B29: ASN-1067 | C29: 39450 | D29: 39450 | E29: 0 | F29: =IF($E29<=0,"On-time","Late") -> On-time | G29: =_xlfn.XLOOKUP(B29,tblARV[ASN/DN '#],tblARV[Country],"Not found") -> Rwanda | H29: =_xlfn.XLOOKUP($B29,tblARV[ASN/DN '#],tblARV[Fulfill Via],"Not found") -> Direct Drop | I29: =_xlfn.XLOOKUP($B29,tblARV[ASN/DN '#],tblARV[Vendor],"Not found") -> Aurobindo Pharma Limited | N29: Kenya | O29: =COUNTIFS($F$20:$F$1349,$O$24,$G$20:$G$1349,$N29) -> 3 | P29: =CHOOSE($Q$19,COUNTIFS($F$20:$F$1349,P$24,$G$20:$G$1349,$N29), COUNTIFS($F$20:$F$1349,P$24,$G$20:$G$1349,$N29,$H$20:$H$1349,$R$19), COUNTIFS($F$20:$F$1349,P$24,$G$20:$G$1349,$N29,$H$20:$H$1349,$R$19)) -> 0 | Q29: =SUM(O29:P29) -> 3 | R29: =+O29/Q29 -> 1 | S29: =P29/Q29 -> 0
B30: ASN-10790 | C30: 40711 | D30: 40711 | E30: 0 | F30: =IF($E30<=0,"On-time","Late") -> On-time | G30: =_xlfn.XLOOKUP(B30,tblARV[ASN/DN '#],tblARV[Country],"Not found") -> Rwanda | H30: =_xlfn.XLOOKUP($B30,tblARV[ASN/DN '#],tblARV[Fulfill Via],"Not found") -> Direct Drop | I30: =_xlfn.XLOOKUP($B30,tblARV[ASN/DN '#],tblARV[Vendor],"Not found") -> HETERO LABS LIMITED | N30: Ethiopia | O30: =COUNTIFS($F$20:$F$1349,$O$24,$G$20:$G$1349,$N30) -> 96 | P30: =CHOOSE($Q$19,COUNTIFS($F$20:$F$1349,P$24,$G$20:$G$1349,$N30), COUNTIFS($F$20:$F$1349,P$24,$G$20:$G$1349,$N30,$H$20:$H$1349,$R$19), COUNTIFS($F$20:$F$1349,P$24,$G$20:$G$1349,$N30,$H$20:$H$1349,$R$19)) -> 11 | Q30: =SUM(O30:P30) -> 107 | R30: =+O30/Q30 -> 0.89719626 | S30: =P30/Q30 -> 0.10280374
B31: ASN-10811 | C31: 40721 | D31: 40721 | E31: 0 | F31: =IF($E31<=0,"On-time","Late") -> On-time | G31: =_xlfn.XLOOKUP(B31,tblARV[ASN/DN '#],tblARV[Country],"Not found") -> Tanzania | H31: =_xlfn.XLOOKUP($B31,tblARV[ASN/DN '#],tblARV[Fulfill Via],"Not found") -> Direct Drop | I31: =_xlfn.XLOOKUP($B31,tblARV[ASN/DN '#],tblARV[Vendor],"Not found") -> LAWRENCE LABORATORIES (SUBSIDIARY OF BRISTOL MYERS SQUIBB) | N31: Burundi | O31: =COUNTIFS($F$20:$F$1349,$O$24,$G$20:$G$1349,$N31) -> 17 | P31: =CHOOSE($Q$19,COUNTIFS($F$20:$F$1349,P$24,$G$20:$G$1349,$N31), COUNTIFS($F$20:$F$1349,P$24,$G$20:$G$1349,$N31,$H$20:$H$1349,$R$19), COUNTIFS($F$20:$F$1349,P$24,$G$20:$G$1349,$N31,$H$20:$H$1349,$R$19)) -> 18 | Q31: =SUM(O31:P31) -> 35 | R31: =+O31/Q31 -> 0.48571429 | S31: =P31/Q31 -> 0.51428571
B32: ASN-11005 | C32: 40738 | D32: 40738 | E32: 0 | F32: =IF($E32<=0,"On-time","Late") -> On-time | G32: =_xlfn.XLOOKUP(B32,tblARV[ASN/DN '#],tblARV[Country],"Not found") -> Tanzania | H32: =_xlfn.XLOOKUP($B32,tblARV[ASN/DN '#],tblARV[Fulfill Via],"Not found") -> Direct Drop | I32: =_xlfn.XLOOKUP($B32,tblARV[ASN/DN '#],tblARV[Vendor],"Not found") -> LAWRENCE LABORATORIES (SUBSIDIARY OF BRISTOL MYERS SQUIBB)
B33: ASN-11009 | C33: 40694 | D33: 40694 | E33: 0 | F33: =IF($E33<=0,"On-time","Late") -> On-time | G33: =_xlfn.XLOOKUP(B33,tblARV[ASN/DN '#],tblARV[Country],"Not found") -> Uganda | H33: =_xlfn.XLOOKUP($B33,tblARV[ASN/DN '#],tblARV[Fulfill Via],"Not found") -> Direct Drop | I33: =_xlfn.XLOOKUP($B33,tblARV[ASN/DN '#],tblARV[Vendor],"Not found") -> ASPEN PHARMACARE
B34: ASN-11026 | C34: 40696 | D34: 40696 | E34: 0 | F34: =IF($E34<=0,"On-time","Late") -> On-time | G34: =_xlfn.XLOOKUP(B34,tblARV[ASN/DN '#],tblARV[Country],"Not found") -> Uganda | H34: =_xlfn.XLOOKUP($B34,tblARV[ASN/DN '#],tblARV[Fulfill Via],"Not found") -> Direct Drop | I34: =_xlfn.XLOOKUP($B34,tblARV[ASN/DN '#],tblARV[Vendor],"Not found") -> ASPEN PHARMACARE
B35: ASN-11156 | C35: 40722 | D35: 40722 | E35: 0 | F35: =IF($E35<=0,"On-time","Late") -> On-time | G35: =_xlfn.XLOOKUP(B35,tblARV[ASN/DN '#],tblARV[Country],"Not found") -> Ethiopia | H35: =_xlfn.XLOOKUP($B35,tblARV[ASN/DN '#],tblARV[Fulfill Via],"Not found") -> Direct Drop | I35: =_xlfn.XLOOKUP($B35,tblARV[ASN/DN '#],tblARV[Vendor],"Not found") -> Aurobindo Pharma Limited | N35: 2.4.3 by Vendor
B36: ASN-11253 | C36: 40725 | D36: 40725 | E36: 0 | F36: =IF($E36<=0,"On-time","Late") -> On-time | G36: =_xlfn.XLOOKUP(B36,tblARV[ASN/DN '#],tblARV[Country],"Not found") -> Ethiopia | H36: =_xlfn.XLOOKUP($B36,tblARV[ASN/DN '#],tblARV[Fulfill Via],"Not found") -> Direct Drop | I36: =_xlfn.XLOOKUP($B36,tblARV[ASN/DN '#],tblARV[Vendor],"Not found") -> MYLAN LABORATORIES LTD (FORMERLY MATRIX LABORATORIES) | N36: Vendor | O36: On-time | P36: Late | Q36: Total | R36: OTD% | S36: LTD%
B37: ASN-11275 | C37: 40807 | D37: 40807 | E37: 0 | F37: =IF($E37<=0,"On-time","Late") -> On-time | G37: =_xlfn.XLOOKUP(B37,tblARV[ASN/DN '#],tblARV[Country],"Not found") -> Ethiopia | H37: =_xlfn.XLOOKUP($B37,tblARV[ASN/DN '#],tblARV[Fulfill Via],"Not found") -> Direct Drop | I37: =_xlfn.XLOOKUP($B37,tblARV[ASN/DN '#],tblARV[Vendor],"Not found") -> Aurobindo Pharma Limited | N37: {=+_xlfn.UNIQUE(I20:I1349)} -> MYLAN LABORATORIES LTD (FORMERLY MATRIX LABORATORIES) | O37: =COUNTIFS($F$20:$F$1349,O$36,$I$20:$I$1349,$N37) -> 63 | P37: =COUNTIFS($F$20:$F$1349,P$36,$I$20:$I$1349,$N37) -> 0 | Q37: =SUM(O37:P37) -> 63 | R37: =+O37/Q37 -> 1 | S37: =P37/Q37 -> 0
B38: ASN-11530 | C38: 40746 | D38: 40746 | E38: 0 | F38: =IF($E38<=0,"On-time","Late") -> On-time | G38: =_xlfn.XLOOKUP(B38,tblARV[ASN/DN '#],tblARV[Country],"Not found") -> Uganda | H38: =_xlfn.XLOOKUP($B38,tblARV[ASN/DN '#],tblARV[Fulfill Via],"Not found") -> Direct Drop | I38: =_xlfn.XLOOKUP($B38,tblARV[ASN/DN '#],tblARV[Vendor],"Not found") -> ASPEN PHARMACARE | N38: Aurobindo Pharma Limited | O38: =COUNTIFS($F$20:$F$1349,O$36,$I$20:$I$1349,$N38) -> 92 | P38: =COUNTIFS($F$20:$F$1349,P$36,$I$20:$I$1349,$N38) -> 13 | Q38: =SUM(O38:P38) -> 105 | R38: =+O38/Q38 -> 0.87619048 | S38: =P38/Q38 -> 0.12380952
B39: ASN-11548 | C39: 40833 | D39: 40833 | E39: 0 | F39: =IF($E39<=0,"On-time","Late") -> On-time | G39: =_xlfn.XLOOKUP(B39,tblARV[ASN/DN '#],tblARV[Country],"Not found") -> Rwanda | H39: =_xlfn.XLOOKUP($B39,tblARV[ASN/DN '#],tblARV[Fulfill Via],"Not found") -> Direct Drop | I39: =_xlfn.XLOOKUP($B39,tblARV[ASN/DN '#],tblARV[Vendor],"Not found") -> HETERO LABS LIMITED | N39: HETERO LABS LIMITED | O39: =COUNTIFS($F$20:$F$1349,O$36,$I$20:$I$1349,$N39) -> 41 | P39: =COUNTIFS($F$20:$F$1349,P$36,$I$20:$I$1349,$N39) -> 0 | Q39: =SUM(O39:P39) -> 41 | R39: =+O39/Q39 -> 1 | S39: =P39/Q39 -> 0
B40: ASN-11623 | C40: 40815 | D40: 40815 | E40: 0 | F40: =IF($E40<=0,"On-time","Late") -> On-time | G40: =_xlfn.XLOOKUP(B40,tblARV[ASN/DN '#],tblARV[Country],"Not found") -> Tanzania | H40: =_xlfn.XLOOKUP($B40,tblARV[ASN/DN '#],tblARV[Fulfill Via],"Not found") -> Direct Drop | I40: =_xlfn.XLOOKUP($B40,tblARV[ASN/DN '#],tblARV[Vendor],"Not found") -> EMCURE PHARMACEUTICALS LTD | N40: ASPEN PHARMACARE | O40: =COUNTIFS($F$20:$F$1349,O$36,$I$20:$I$1349,$N40) -> 29 | P40: =COUNTIFS($F$20:$F$1349,P$36,$I$20:$I$1349,$N40) -> 0 | Q40: =SUM(O40:P40) -> 29 | R40: =+O40/Q40 -> 1 | S40: =P40/Q40 -> 0
B41: ASN-11688 | C41: 40780 | D41: 40780 | E41: 0 | F41: =IF($E41<=0,"On-time","Late") -> On-time | G41: =_xlfn.XLOOKUP(B41,tblARV[ASN/DN '#],tblARV[Country],"Not found") -> Ethiopia | H41: =_xlfn.XLOOKUP($B41,tblARV[ASN/DN '#],tblARV[Fulfill Via],"Not found") -> Direct Drop | I41: =_xlfn.XLOOKUP($B41,tblARV[ASN/DN '#],tblARV[Vendor],"Not found") -> Aurobindo Pharma Limited | N41: MERCK SHARP & DOHME IDEA GMBH (FORMALLY MERCK SHARP & DOHME B.V.) | O41: =COUNTIFS($F$20:$F$1349,O$36,$I$20:$I$1349,$N41) -> 19 | P41: =COUNTIFS($F$20:$F$1349,P$36,$I$20:$I$1349,$N41) -> 0 | Q41: =SUM(O41:P41) -> 19 | R41: =+O41/Q41 -> 1 | S41: =P41/Q41 -> 0
B42: ASN-1194 | C42: 39475 | D42: 39475 | E42: 0 | F42: =IF($E42<=0,"On-time","Late") -> On-time | G42: =_xlfn.XLOOKUP(B42,tblARV[ASN/DN '#],tblARV[Country],"Not found") -> Rwanda | H42: =_xlfn.XLOOKUP($B42,tblARV[ASN/DN '#],tblARV[Fulfill Via],"Not found") -> Direct Drop | I42: =_xlfn.XLOOKUP($B42,tblARV[ASN/DN '#],tblARV[Vendor],"Not found") -> MYLAN LABORATORIES LTD (FORMERLY MATRIX LABORATORIES) | N42: LAWRENCE LABORATORIES (SUBSIDIARY OF BRISTOL MYERS SQUIBB) | O42: =COUNTIFS($F$20:$F$1349,O$36,$I$20:$I$1349,$N42) -> 5 | P42: =COUNTIFS($F$20:$F$1349,P$36,$I$20:$I$1349,$N42) -> 0 | Q42: =SUM(O42:P42) -> 5 | R42: =+O42/Q42 -> 1 | S42: =P42/Q42 -> 0
B43: ASN-12088 | C43: 40840 | D43: 40840 | E43: 0 | F43: =IF($E43<=0,"On-time","Late") -> On-time | G43: =_xlfn.XLOOKUP(B43,tblARV[ASN/DN '#],tblARV[Country],"Not found") -> Tanzania | H43: =_xlfn.XLOOKUP($B43,tblARV[ASN/DN '#],tblARV[Fulfill Via],"Not found") -> Direct Drop | I43: =_xlfn.XLOOKUP($B43,tblARV[ASN/DN '#],tblARV[Vendor],"Not found") -> ABBVIE LOGISTICS (FORMERLY ABBOTT LOGISTICS BV) | N43: EMCURE PHARMACEUTICALS LTD | O43: =COUNTIFS($F$20:$F$1349,O$36,$I$20:$I$1349,$N43) -> 21 | P43: =COUNTIFS($F$20:$F$1349,P$36,$I$20:$I$1349,$N43) -> 0 | Q43: =SUM(O43:P43) -> 21 | R43: =+O43/Q43 -> 1 | S43: =P43/Q43 -> 0
B44: ASN-12230 | C44: 40813 | D44: 40813 | E44: 0 | F44: =IF($E44<=0,"On-time","Late") -> On-time | G44: =_xlfn.XLOOKUP(B44,tblARV[ASN/DN '#],tblARV[Country],"Not found") -> Rwanda | H44: =_xlfn.XLOOKUP($B44,tblARV[ASN/DN '#],tblARV[Fulfill Via],"Not found") -> Direct Drop | I44: =_xlfn.XLOOKUP($B44,tblARV[ASN/DN '#],tblARV[Vendor],"Not found") -> Aurobindo Pharma Limited | N44: ABBVIE LOGISTICS (FORMERLY ABBOTT LOGISTICS BV) | O44: =COUNTIFS($F$20:$F$1349,O$36,$I$20:$I$1349,$N44) -> 73 | P44: =COUNTIFS($F$20:$F$1349,P$36,$I$20:$I$1349,$N44) -> 0 | Q44: =SUM(O44:P44) -> 73 | R44: =+O44/Q44 -> 1 | S44: =P44/Q44 -> 0
B45: ASN-12361 | C45: 40847 | D45: 40847 | E45: 0 | F45: =IF($E45<=0,"On-time","Late") -> On-time | G45: =_xlfn.XLOOKUP(B45,tblARV[ASN/DN '#],tblARV[Country],"Not found") -> Ethiopia | H45: =_xlfn.XLOOKUP($B45,tblARV[ASN/DN '#],tblARV[Fulfill Via],"Not found") -> Direct Drop | I45: =_xlfn.XLOOKUP($B45,tblARV[ASN/DN '#],tblARV[Vendor],"Not found") -> Aurobindo Pharma Limited | N45: STRIDES ARCOLAB LIMITED | O45: =COUNTIFS($F$20:$F$1349,O$36,$I$20:$I$1349,$N45) -> 11 | P45: =COUNTIFS($F$20:$F$1349,P$36,$I$20:$I$1349,$N45) -> 0 | Q45: =SUM(O45:P45) -> 11 | R45: =+O45/Q45 -> 1 | S45: =P45/Q45 -> 0
B46: ASN-124 | C46: 39084 | D46: 39084 | E46: 0 | F46: =IF($E46<=0,"On-time","Late") -> On-time | G46: =_xlfn.XLOOKUP(B46,tblARV[ASN/DN '#],tblARV[Country],"Not found") -> Uganda | H46: =_xlfn.XLOOKUP($B46,tblARV[ASN/DN '#],tblARV[Fulfill Via],"Not found") -> Direct Drop | I46: =_xlfn.XLOOKUP($B46,tblARV[ASN/DN '#],tblARV[Vendor],"Not found") -> STRIDES ARCOLAB LIMITED | N46: SUN PHARMACEUTICAL INDUSTRIES LTD (RANBAXY LABORATORIES LIMITED) | O46: =COUNTIFS($F$20:$F$1349,O$36,$I$20:$I$1349,$N46) -> 1 | P46: =COUNTIFS($F$20:$F$1349,P$36,$I$20:$I$1349,$N46) -> 0 | Q46: =SUM(O46:P46) -> 1 | R46: =+O46/Q46 -> 1 | S46: =P46/Q46 -> 0
B47: ASN-12478 | C47: 40835 | D47: 40835 | E47: 0 | F47: =IF($E47<=0,"On-time","Late") -> On-time | G47: =_xlfn.XLOOKUP(B47,tblARV[ASN/DN '#],tblARV[Country],"Not found") -> Uganda | H47: =_xlfn.XLOOKUP($B47,tblARV[ASN/DN '#],tblARV[Fulfill Via],"Not found") -> Direct Drop | I47: =_xlfn.XLOOKUP($B47,tblARV[ASN/DN '#],tblARV[Vendor],"Not found") -> MERCK SHARP & DOHME IDEA GMBH (FORMALLY MERCK SHARP & DOHME B.V.) | N47: CIPLA LIMITED | O47: =COUNTIFS($F$20:$F$1349,O$36,$I$20:$I$1349,$N47) -> 37 | P47: =COUNTIFS($F$20:$F$1349,P$36,$I$20:$I$1349,$N47) -> 0 | Q47: =SUM(O47:P47) -> 37 | R47: =+O47/Q47 -> 1 | S47: =P47/Q47 -> 0
B48: ASN-125 | C48: 39073 | D48: 39073 | E48: 0 | F48: =IF($E48<=0,"On-time","Late") -> On-time | G48: =_xlfn.XLOOKUP(B48,tblARV[ASN/DN '#],tblARV[Country],"Not found") -> Uganda | H48: =_xlfn.XLOOKUP($B48,tblARV[ASN/DN '#],tblARV[Fulfill Via],"Not found") -> Direct Drop | I48: =_xlfn.XLOOKUP($B48,tblARV[ASN/DN '#],tblARV[Vendor],"Not found") -> SUN PHARMACEUTICAL INDUSTRIES LTD (RANBAXY LABORATORIES LIMITED) | N48: Hoffmann-La Roche ltd Basel | O48: =COUNTIFS($F$20:$F$1349,O$36,$I$20:$I$1349,$N48) -> 8 | P48: =COUNTIFS($F$20:$F$1349,P$36,$I$20:$I$1349,$N48) -> 0 | Q48: =SUM(O48:P48) -> 8 | R48: =+O48/Q48 -> 1 | S48: =P48/Q48 -> 0
B49: ASN-12601 | C49: 40890 | D49: 40890 | E49: 0 | F49: =IF($E49<=0,"On-time","Late") -> On-time | G49: =_xlfn.XLOOKUP(B49,tblARV[ASN/DN '#],tblARV[Country],"Not found") -> Rwanda | H49: =_xlfn.XLOOKUP($B49,tblARV[ASN/DN '#],tblARV[Fulfill Via],"Not found") -> Direct Drop | I49: =_xlfn.XLOOKUP($B49,tblARV[ASN/DN '#],tblARV[Vendor],"Not found") -> CIPLA LIMITED | N49: BRISTOL-MYERS SQUIBB | O49: =COUNTIFS($F$20:$F$1349,O$36,$I$20:$I$1349,$N49) -> 13 | P49: =COUNTIFS($F$20:$F$1349,P$36,$I$20:$I$1349,$N49) -> 0 | Q49: =SUM(O49:P49) -> 13 | R49: =+O49/Q49 -> 1 | S49: =P49/Q49 -> 0
... B55: ASN-13223 | C55: 40922 | D55: 40922 | E55: 0 | F55: =IF($E55<=0,"On-time","Late") -> On-time | G55: =_xlfn.XLOOKUP(B55,tblARV[ASN/DN '#],tblARV[Country],"Not found") -> Uganda | H55: =_xlfn.XLOOKUP($B55,tblARV[ASN/DN '#],tblARV[Fulfill Via],"Not found") -> Direct Drop | I55: =_xlfn.XLOOKUP($B55,tblARV[ASN/DN '#],tblARV[Vendor],"Not found") -> Hoffmann-La Roche ltd Basel | N55: SCMS from RDC | O55: =COUNTIFS($F$20:$F$1349,O$36,$I$20:$I$1349,$N55) -> 731 | P55: =COUNTIFS($F$20:$F$1349,P$36,$I$20:$I$1349,$N55) -> 161 | Q55: =SUM(O55:P55) -> 892 | R55: =+O55/Q55 -> 0.81950673 | S55: =P55/Q55 -> 0.18049327
B56: ASN-1329 | C56: 39511 | D56: 39511 | E56: 0 | F56: =IF($E56<=0,"On-time","Late") -> On-time | G56: =_xlfn.XLOOKUP(B56,tblARV[ASN/DN '#],tblARV[Country],"Not found") -> Ethiopia | H56: =_xlfn.XLOOKUP($B56,tblARV[ASN/DN '#],tblARV[Fulfill Via],"Not found") -> Direct Drop | I56: =_xlfn.XLOOKUP($B56,tblARV[ASN/DN '#],tblARV[Vendor],"Not found") -> ASPEN PHARMACARE
B57: ASN-13341 | C57: 41012 | D57: 41012 | E57: 0 | F57: =IF($E57<=0,"On-time","Late") -> On-time | G57: =_xlfn.XLOOKUP(B57,tblARV[ASN/DN '#],tblARV[Country],"Not found") -> Rwanda | H57: =_xlfn.XLOOKUP($B57,tblARV[ASN/DN '#],tblARV[Fulfill Via],"Not found") -> Direct Drop | I57: =_xlfn.XLOOKUP($B57,tblARV[ASN/DN '#],tblARV[Vendor],"Not found") -> Aurobindo Pharma Limited
B58: ASN-13371 | C58: 40932 | D58: 40932 | E58: 0 | F58: =IF($E58<=0,"On-time","Late") -> On-time | G58: =_xlfn.XLOOKUP(B58,tblARV[ASN/DN '#],tblARV[Country],"Not found") -> Rwanda | H58: =_xlfn.XLOOKUP($B58,tblARV[ASN/DN '#],tblARV[Fulfill Via],"Not found") -> Direct Drop | I58: =_xlfn.XLOOKUP($B58,tblARV[ASN/DN '#],tblARV[Vendor],"Not found") -> Aurobindo Pharma Limited
B59: ASN-13372 | C59: 40932 | D59: 40933 | E59: 1 | F59: =IF($E59<=0,"On-time","Late") -> Late | G59: =_xlfn.XLOOKUP(B59,tblARV[ASN/DN '#],tblARV[Country],"Not found") -> Rwanda | H59: =_xlfn.XLOOKUP($B59,tblARV[ASN/DN '#],tblARV[Fulfill Via],"Not found") -> Direct Drop | I59: =_xlfn.XLOOKUP($B59,tblARV[ASN/DN '#],tblARV[Vendor],"Not found") -> Aurobindo Pharma Limited
B60: ASN-13373 | C60: 40932 | D60: 40934 | E60: 2 | F60: =IF($E60<=0,"On-time","Late") -> Late | G60: =_xlfn.XLOOKUP(B60,tblARV[ASN/DN '#],tblARV[Country],"Not found") -> Rwanda | H60: =_xlfn.XLOOKUP($B60,tblARV[ASN/DN '#],tblARV[Fulfill Via],"Not found") -> Direct Drop | I60: =_xlfn.XLOOKUP($B60,tblARV[ASN/DN '#],tblARV[Vendor],"Not found") -> Aurobindo Pharma Limited
B61: ASN-13435 | C61: 40914 | D61: 40914 | E61: 0 | F61: =IF($E61<=0,"On-time","Late") -> On-time | G61: =_xlfn.XLOOKUP(B61,tblARV[ASN/DN '#],tblARV[Country],"Not found") -> Uganda | H61: =_xlfn.XLOOKUP($B61,tblARV[ASN/DN '#],tblARV[Fulfill Via],"Not found") -> Direct Drop | I61: =_xlfn.XLOOKUP($B61,tblARV[ASN/DN '#],tblARV[Vendor],"Not found") -> ASPEN PHARMACARE
B62: ASN-13437 | C62: 40912 | D62: 40912 | E62: 0 | F62: =IF($E62<=0,"On-time","Late") -> On-time | G62: =_xlfn.XLOOKUP(B62,tblARV[ASN/DN '#],tblARV[Country],"Not found") -> Uganda | H62: =_xlfn.XLOOKUP($B62,tblARV[ASN/DN '#],tblARV[Fulfill Via],"Not found") -> Direct Drop | I62: =_xlfn.XLOOKUP($B62,tblARV[ASN/DN '#],tblARV[Vendor],"Not found") -> ASPEN PHARMACARE
B63: ASN-13476 | C63: 40932 | D63: 40932 | E63: 0 | F63: =IF($E63<=0,"On-time","Late") -> On-time | G63: =_xlfn.XLOOKUP(B63,tblARV[ASN/DN '#],tblARV[Country],"Not found") -> Rwanda | H63: =_xlfn.XLOOKUP($B63,tblARV[ASN/DN '#],tblARV[Fulfill Via],"Not found") -> Direct Drop | I63: =_xlfn.XLOOKUP($B63,tblARV[ASN/DN '#],tblARV[Vendor],"Not found") -> Aurobindo Pharma Limited
B64: ASN-13518 | C64: 40935 | D64: 40935 | E64: 0 | F64: =IF($E64<=0,"On-time","Late") -> On-time | G64: =_xlfn.XLOOKUP(B64,tblARV[ASN/DN '#],tblARV[Country],"Not found") -> Rwanda | H64: =_xlfn.XLOOKUP($B64,tblARV[ASN/DN '#],tblARV[Fulfill Via],"Not found") -> Direct Drop | I64: =_xlfn.XLOOKUP($B64,tblARV[ASN/DN '#],tblARV[Vendor],"Not found") -> ABBVIE LOGISTICS (FORMERLY ABBOTT LOGISTICS BV)
B65: ASN-13559 | C65: 40941 | D65: 40941 | E65: 0 | F65: =IF($E65<=0,"On-time","Late") -> On-time | G65: =_xlfn.XLOOKUP(B65,tblARV[ASN/DN '#],tblARV[Country],"Not found") -> Rwanda | H65: =_xlfn.XLOOKUP($B65,tblARV[ASN/DN '#],tblARV[Fulfill Via],"Not found") -> Direct Drop | I65: =_xlfn.XLOOKUP($B65,tblARV[ASN/DN '#],tblARV[Vendor],"Not found") -> ABBVIE LOGISTICS (FORMERLY ABBOTT LOGISTICS BV)
B66: ASN-13697 | C66: 40953 | D66: 40953 | E66: 0 | F66: =IF($E66<=0,"On-time","Late") -> On-time | G66: =_xlfn.XLOOKUP(B66,tblARV[ASN/DN '#],tblARV[Country],"Not found") -> Uganda | H66: =_xlfn.XLOOKUP($B66,tblARV[ASN/DN '#],tblARV[Fulfill Via],"Not found") -> Direct Drop | I66: =_xlfn.XLOOKUP($B66,tblARV[ASN/DN '#],tblARV[Vendor],"Not found") -> MERCK SHARP & DOHME IDEA GMBH (FORMALLY MERCK SHARP & DOHME B.V.)
B67: ASN-13722 | C67: 40966 | D67: 40966 | E67: 0 | F67: =IF($E67<=0,"On-time","Late") -> On-time | G67: =_xlfn.XLOOKUP(B67,tblARV[ASN/DN '#],tblARV[Country],"Not found") -> Rwanda | H67: =_xlfn.XLOOKUP($B67,tblARV[ASN/DN '#],tblARV[Fulfill Via],"Not found") -> Direct Drop | I67: =_xlfn.XLOOKUP($B67,tblARV[ASN/DN '#],tblARV[Vendor],"Not found") -> ABBVIE LOGISTICS (FORMERLY ABBOTT LOGISTICS BV)
... B1349: DN-998 | C1349: 39797 | D1349: 39797 | E1349: 0 | F1349: =IF($E1349<=0,"On-time","Late") -> On-time | G1349: =_xlfn.XLOOKUP(B1349,tblARV[ASN/DN '#],tblARV[Country],"Not found") -> Uganda | H1349: =_xlfn.XLOOKUP($B1349,tblARV[ASN/DN '#],tblARV[Fulfill Via],"Not found") -> From RDC | I1349: =_xlfn.XLOOKUP($B1349,tblARV[ASN/DN '#],tblARV[Vendor],"Not found") -> SCMS from RDC

Sheet Dashboard
B6: 1. Timely Delivery - Delivery Reliability by Country | J6: 1. Timely Delivery - Delivery Reliability By Fulfillment Channel
B8: Fulfillment Channel:
B10: =+Calculation!N24 -> Country | C10: =+Calculation!O24 -> On-time | D10: =+Calculation!P24 -> Late | E10: =+Calculation!Q24 -> Total | F10: =+Calculation!R24 -> OTD%
B11: =Calculation!N25 -> Uganda | C11: =Calculation!O25 -> 477 | D11: =Calculation!P25 -> 68 | E11: =Calculation!Q25 -> 545 | F11: =+G11 -> 0.87522936 | G11: =Calculation!R25 -> 0.87522936
B12: =Calculation!N26 -> Tanzania | C12: =Calculation!O26 -> 268 | D12: =Calculation!P26 -> 45 | E12: =Calculation!Q26 -> 313 | F12: =+G12 -> 0.85623003 | G12: =Calculation!R26 -> 0.85623003
B13: =Calculation!N27 -> South Sudan | C13: =Calculation!O27 -> 19 | D13: =Calculation!P27 -> 5 | E13: =Calculation!Q27 -> 24 | F13: =+G13 -> 0.79166667 | G13: =Calculation!R27 -> 0.79166667
B14: =Calculation!N28 -> Rwanda | C14: =Calculation!O28 -> 276 | D14: =Calculation!P28 -> 27 | E14: =Calculation!Q28 -> 303 | F14: =+G14 -> 0.91089109 | G14: =Calculation!R28 -> 0.91089109
B15: =Calculation!N29 -> Kenya | C15: =Calculation!O29 -> 3 | D15: =Calculation!P29 -> 0 | E15: =Calculation!Q29 -> 3 | F15: =+G15 -> 1 | G15: =Calculation!R29 -> 1
B16: =Calculation!N30 -> Ethiopia | C16: =Calculation!O30 -> 96 | D16: =Calculation!P30 -> 11 | E16: =Calculation!Q30 -> 107 | F16: =+G16 -> 0.89719626 | G16: =Calculation!R30 -> 0.89719626
B17: =Calculation!N31 -> Burundi | C17: =Calculation!O31 -> 17 | D17: =Calculation!P31 -> 18 | E17: =Calculation!Q31 -> 35 | F17: =+G17 -> 0.48571429 | G17: =Calculation!R31 -> 0.48571429
B18: Total | C18: =SUM(C11:C17) -> 1156 | D18: =SUM(D11:D17) -> 174 | E18: =SUM(E11:E17) -> 1330 | F18: =C18/$E$18 -> 0.86917293
B20: 2. Procurement Cost - Weighted Pack Price Trend by Product | J20: Reliable - Commodity Value by Fulfillment Channel

Sheet Management Report
B2: ARV SUPPLY CHAIN | MANAGEMENT PERFORMANCE REPORT
B3: East Africa • 2006–2015 • Seven countries • Historical USAID ARV commodity shipment data
B5: TOTAL DELIVERIES | E5: ON-TIME DELIVERY | H5: AVERAGE LATE DELAY | K5: COMMODITY VALUE
B6: 1330 | E6: 0.8692 | H6: 21.49 days | K6: $282.65M
B9: EXECUTIVE ASSESSMENT
B10: The historical ARV distribution records show that 86.92% of evaluated deliveries arrived on or before schedule, but late shipments averaged 21.49 days beyond the scheduled date. Recorded weighted pack prices declined across major ARV presentations, while distribution activity was concentrated in the Regional Distribution Centre (RDC) channel. The immediate management priority is to investigate RDC delivery delays and weak destination-country performance, alongside continued product-specific price monitoring. | C10: The historical ARV distribution records show that 86.92% of evaluated deliveries arrived on or before schedule, but late shipments averaged 21.49 days beyond the scheduled date. Recorded weighted pack prices declined across major ARV presentations, while distribution activity was concentrated in the Regional Distribution Centre (RDC) channel. The immediate management priority is to investigate RDC delivery delays and weak destination-country performance, alongside continued product-specific price monitoring. | D10: The historical ARV distribution records show that 86.92% of evaluated deliveries arrived on or before schedule, but late shipments averaged 21.49 days beyond the scheduled date. Recorded weighted pack prices declined across major ARV presentations, while distribution activity was concentrated in the Regional Distribution Centre (RDC) channel. The immediate management priority is to investigate RDC delivery delays and weak destination-country performance, alongside continued product-specific price monitoring. | E10: The historical ARV distribution records show that 86.92% of evaluated deliveries arrived on or before schedule, but late shipments averaged 21.49 days beyond the scheduled date. Recorded weighted pack prices declined across major ARV presentations, while distribution activity was concentrated in the Regional Distribution Centre (RDC) channel. The immediate management priority is to investigate RDC delivery delays and weak destination-country performance, alongside continued product-specific price monitoring. | F10: The historical ARV distribution records show that 86.92% of evaluated deliveries arrived on or before schedule, but late shipments averaged 21.49 days beyond the scheduled date. Recorded weighted pack prices declined across major ARV presentations, while distribution activity was concentrated in the Regional Distribution Centre (RDC) channel. The immediate management priority is to investigate RDC delivery delays and weak destination-country performance, alongside continued product-specific price monitoring. | G10: The historical ARV distribution records show that 86.92% of evaluated deliveries arrived on or before schedule, but late shipments averaged 21.49 days beyond the scheduled date. Recorded weighted pack prices declined across major ARV presentations, while distribution activity was concentrated in the Regional Distribution Centre (RDC) channel. The immediate management priority is to investigate RDC delivery delays and weak destination-country performance, alongside continued product-specific price monitoring. | H10: The historical ARV distribution records show that 86.92% of evaluated deliveries arrived on or before schedule, but late shipments averaged 21.49 days beyond the scheduled date. Recorded weighted pack prices declined across major ARV presentations, while distribution activity was concentrated in the Regional Distribution Centre (RDC) channel. The immediate management priority is to investigate RDC delivery delays and weak destination-country performance, alongside continued product-specific price monitoring. | I10: The historical ARV distribution records show that 86.92% of evaluated deliveries arrived on or before schedule, but late shipments averaged 21.49 days beyond the scheduled date. Recorded weighted pack prices declined across major ARV presentations, while distribution activity was concentrated in the Regional Distribution Centre (RDC) channel. The immediate management priority is to investigate RDC delivery delays and weak destination-country performance, alongside continued product-specific price monitoring. | J10: The historical ARV distribution records show that 86.92% of evaluated deliveries arrived on or before schedule, but late shipments averaged 21.49 days beyond the scheduled date. Recorded weighted pack prices declined across major ARV presentations, while distribution activity was concentrated in the Regional Distribution Centre (RDC) channel. The immediate management priority is to investigate RDC delivery delays and weak destination-country performance, alongside continued product-specific price monitoring. | K10: The historical ARV distribution records show that 86.92% of evaluated deliveries arrived on or before schedule, but late shipments averaged 21.49 days beyond the scheduled date. Recorded weighted pack prices declined across major ARV presentations, while distribution activity was concentrated in the Regional Distribution Centre (RDC) channel. The immediate management priority is to investigate RDC delivery delays and weak destination-country performance, alongside continued product-specific price monitoring. | L10: The historical ARV distribution records show that 86.92% of evaluated deliveries arrived on or before schedule, but late shipments averaged 21.49 days beyond the scheduled date. Recorded weighted pack prices declined across major ARV presentations, while distribution activity was concentrated in the Regional Distribution Centre (RDC) channel. The immediate management priority is to investigate RDC delivery delays and weak destination-country performance, alongside continued product-specific price monitoring.
B11: The historical ARV distribution records show that 86.92% of evaluated deliveries arrived on or before schedule, but late shipments averaged 21.49 days beyond the scheduled date. Recorded weighted pack prices declined across major ARV presentations, while distribution activity was concentrated in the Regional Distribution Centre (RDC) channel. The immediate management priority is to investigate RDC delivery delays and weak destination-country performance, alongside continued product-specific price monitoring. | C11: The historical ARV distribution records show that 86.92% of evaluated deliveries arrived on or before schedule, but late shipments averaged 21.49 days beyond the scheduled date. Recorded weighted pack prices declined across major ARV presentations, while distribution activity was concentrated in the Regional Distribution Centre (RDC) channel. The immediate management priority is to investigate RDC delivery delays and weak destination-country performance, alongside continued product-specific price monitoring. | D11: The historical ARV distribution records show that 86.92% of evaluated deliveries arrived on or before schedule, but late shipments averaged 21.49 days beyond the scheduled date. Recorded weighted pack prices declined across major ARV presentations, while distribution activity was concentrated in the Regional Distribution Centre (RDC) channel. The immediate management priority is to investigate RDC delivery delays and weak destination-country performance, alongside continued product-specific price monitoring. | E11: The historical ARV distribution records show that 86.92% of evaluated deliveries arrived on or before schedule, but late shipments averaged 21.49 days beyond the scheduled date. Recorded weighted pack prices declined across major ARV presentations, while distribution activity was concentrated in the Regional Distribution Centre (RDC) channel. The immediate management priority is to investigate RDC delivery delays and weak destination-country performance, alongside continued product-specific price monitoring. | F11: The historical ARV distribution records show that 86.92% of evaluated deliveries arrived on or before schedule, but late shipments averaged 21.49 days beyond the scheduled date. Recorded weighted pack prices declined across major ARV presentations, while distribution activity was concentrated in the Regional Distribution Centre (RDC) channel. The immediate management priority is to investigate RDC delivery delays and weak destination-country performance, alongside continued product-specific price monitoring. | G11: The historical ARV distribution records show that 86.92% of evaluated deliveries arrived on or before schedule, but late shipments averaged 21.49 days beyond the scheduled date. Recorded weighted pack prices declined across major ARV presentations, while distribution activity was concentrated in the Regional Distribution Centre (RDC) channel. The immediate management priority is to investigate RDC delivery delays and weak destination-country performance, alongside continued product-specific price monitoring. | H11: The historical ARV distribution records show that 86.92% of evaluated deliveries arrived on or before schedule, but late shipments averaged 21.49 days beyond the scheduled date. Recorded weighted pack prices declined across major ARV presentations, while distribution activity was concentrated in the Regional Distribution Centre (RDC) channel. The immediate management priority is to investigate RDC delivery delays and weak destination-country performance, alongside continued product-specific price monitoring. | I11: The historical ARV distribution records show that 86.92% of evaluated deliveries arrived on or before schedule, but late shipments averaged 21.49 days beyond the scheduled date. Recorded weighted pack prices declined across major ARV presentations, while distribution activity was concentrated in the Regional Distribution Centre (RDC) channel. The immediate management priority is to investigate RDC delivery delays and weak destination-country performance, alongside continued product-specific price monitoring. | J11: The historical ARV distribution records show that 86.92% of evaluated deliveries arrived on or before schedule, but late shipments averaged 21.49 days beyond the scheduled date. Recorded weighted pack prices declined across major ARV presentations, while distribution activity was concentrated in the Regional Distribution Centre (RDC) channel. The immediate management priority is to investigate RDC delivery delays and weak destination-country performance, alongside continued product-specific price monitoring. | K11: The historical ARV distribution records show that 86.92% of evaluated deliveries arrived on or before schedule, but late shipments averaged 21.49 days beyond the scheduled date. Recorded weighted pack prices declined across major ARV presentations, while distribution activity was concentrated in the Regional Distribution Centre (RDC) channel. The immediate management priority is to investigate RDC delivery delays and weak destination-country performance, alongside continued product-specific price monitoring. | L11: The historical ARV distribution records show that 86.92% of evaluated deliveries arrived on or before schedule, but late shipments averaged 21.49 days beyond the scheduled date. Recorded weighted pack prices declined across major ARV presentations, while distribution activity was concentrated in the Regional Distribution Centre (RDC) channel. The immediate management priority is to investigate RDC delivery delays and weak destination-country performance, alongside continued product-specific price monitoring.
B13: 1 TIMELY DELIVERY
B14: Delivery timeliness was assessed using 1,330 unique ASN/DN references, avoiding double counting when a delivery contained multiple product lines. An on-time delivery arrived on or before its scheduled delivery date. | C14: Delivery timeliness was assessed using 1,330 unique ASN/DN references, avoiding double counting when a delivery contained multiple product lines. An on-time delivery arrived on or before its scheduled delivery date. | D14: Delivery timeliness was assessed using 1,330 unique ASN/DN references, avoiding double counting when a delivery contained multiple product lines. An on-time delivery arrived on or before its scheduled delivery date. | E14: Delivery timeliness was assessed using 1,330 unique ASN/DN references, avoiding double counting when a delivery contained multiple product lines. An on-time delivery arrived on or before its scheduled delivery date. | F14: Delivery timeliness was assessed using 1,330 unique ASN/DN references, avoiding double counting when a delivery contained multiple product lines. An on-time delivery arrived on or before its scheduled delivery date. | G14: Delivery timeliness was assessed using 1,330 unique ASN/DN references, avoiding double counting when a delivery contained multiple product lines. An on-time delivery arrived on or before its scheduled delivery date. | H14: Delivery timeliness was assessed using 1,330 unique ASN/DN references, avoiding double counting when a delivery contained multiple product lines. An on-time delivery arrived on or before its scheduled delivery date. | I14: Delivery timeliness was assessed using 1,330 unique ASN/DN references, avoiding double counting when a delivery contained multiple product lines. An on-time delivery arrived on or before its scheduled delivery date. | J14: Delivery timeliness was assessed using 1,330 unique ASN/DN references, avoiding double counting when a delivery contained multiple product lines. An on-time delivery arrived on or before its scheduled delivery date. | K14: Delivery timeliness was assessed using 1,330 unique ASN/DN references, avoiding double counting when a delivery contained multiple product lines. An on-time delivery arrived on or before its scheduled delivery date. | L14: Delivery timeliness was assessed using 1,330 unique ASN/DN references, avoiding double counting when a delivery contained multiple product lines. An on-time delivery arrived on or before its scheduled delivery date.
B15: Delivery timeliness was assessed using 1,330 unique ASN/DN references, avoiding double counting when a delivery contained multiple product lines. An on-time delivery arrived on or before its scheduled delivery date. | C15: Delivery timeliness was assessed using 1,330 unique ASN/DN references, avoiding double counting when a delivery contained multiple product lines. An on-time delivery arrived on or before its scheduled delivery date. | D15: Delivery timeliness was assessed using 1,330 unique ASN/DN references, avoiding double counting when a delivery contained multiple product lines. An on-time delivery arrived on or before its scheduled delivery date. | E15: Delivery timeliness was assessed using 1,330 unique ASN/DN references, avoiding double counting when a delivery contained multiple product lines. An on-time delivery arrived on or before its scheduled delivery date. | F15: Delivery timeliness was assessed using 1,330 unique ASN/DN references, avoiding double counting when a delivery contained multiple product lines. An on-time delivery arrived on or before its scheduled delivery date. | G15: Delivery timeliness was assessed using 1,330 unique ASN/DN references, avoiding double counting when a delivery contained multiple product lines. An on-time delivery arrived on or before its scheduled delivery date. | H15: Delivery timeliness was assessed using 1,330 unique ASN/DN references, avoiding double counting when a delivery contained multiple product lines. An on-time delivery arrived on or before its scheduled delivery date. | I15: Delivery timeliness was assessed using 1,330 unique ASN/DN references, avoiding double counting when a delivery contained multiple product lines. An on-time delivery arrived on or before its scheduled delivery date. | J15: Delivery timeliness was assessed using 1,330 unique ASN/DN references, avoiding double counting when a delivery contained multiple product lines. An on-time delivery arrived on or before its scheduled delivery date. | K15: Delivery timeliness was assessed using 1,330 unique ASN/DN references, avoiding double counting when a delivery contained multiple product lines. An on-time delivery arrived on or before its scheduled delivery date. | L15: Delivery timeliness was assessed using 1,330 unique ASN/DN references, avoiding double counting when a delivery contained multiple product lines. An on-time delivery arrived on or before its scheduled delivery date.
B17: MEASURE | E17: EVIDENCE | H17: MANAGEMENT RELEVANCE
B18: Overall delivery performance | E18: 1,156 on time / 174 late; OTD 86.92% | H18: Most evaluated deliveries met schedule, but 13.08% arrived late.
B19: Severity of late delivery | E19: Average 21.49 days; median 12 days; maximum 280 days | H19: The difference between average and median suggests that some lengthy delays increase the mean. The 280-day case merits validation.
B20: Destination-country performance | E20: Burundi: 48.57% OTD (17/35); Rwanda: 91.09% (276/303) | H20: Burundi is the clearest proportional concern; Kenya’s 100% OTD is based on just 3 deliveries.
B21: Fulfillment-channel performance | E21: Direct Drop: 97.03% (425/438); RDC: 81.95% (731/892) | H21: RDC accounts for 161 of the 174 late deliveries, indicating a priority for operational review.
B22: Direct Drop vendor observation | E22: Aurobindo: 87.62% OTD (92/105); 13 late deliveries | H22: All recorded Direct Drop delays were associated with this vendor; investigate events without assuming causation.
B24: 2 REASONABLE PROCUREMENT COST
B25: Recorded commodity value totaled $282.65 million across 35.12 million packs. A quantity-weighted pack price (sum of line-item value ÷ sum of pack quantity) was used to assess historical price movement for identical ARV presentations, rather than combining unlike medicines into one price comparison. | C25: Recorded commodity value totaled $282.65 million across 35.12 million packs. A quantity-weighted pack price (sum of line-item value ÷ sum of pack quantity) was used to assess historical price movement for identical ARV presentations, rather than combining unlike medicines into one price comparison. | D25: Recorded commodity value totaled $282.65 million across 35.12 million packs. A quantity-weighted pack price (sum of line-item value ÷ sum of pack quantity) was used to assess historical price movement for identical ARV presentations, rather than combining unlike medicines into one price comparison. | E25: Recorded commodity value totaled $282.65 million across 35.12 million packs. A quantity-weighted pack price (sum of line-item value ÷ sum of pack quantity) was used to assess historical price movement for identical ARV presentations, rather than combining unlike medicines into one price comparison. | F25: Recorded commodity value totaled $282.65 million across 35.12 million packs. A quantity-weighted pack price (sum of line-item value ÷ sum of pack quantity) was used to assess historical price movement for identical ARV presentations, rather than combining unlike medicines into one price comparison. | G25: Recorded commodity value totaled $282.65 million across 35.12 million packs. A quantity-weighted pack price (sum of line-item value ÷ sum of pack quantity) was used to assess historical price movement for identical ARV presentations, rather than combining unlike medicines into one price comparison. | H25: Recorded commodity value totaled $282.65 million across 35.12 million packs. A quantity-weighted pack price (sum of line-item value ÷ sum of pack quantity) was used to assess historical price movement for identical ARV presentations, rather than combining unlike medicines into one price comparison. | I25: Recorded commodity value totaled $282.65 million across 35.12 million packs. A quantity-weighted pack price (sum of line-item value ÷ sum of pack quantity) was used to assess historical price movement for identical ARV presentations, rather than combining unlike medicines into one price comparison. | J25: Recorded commodity value totaled $282.65 million across 35.12 million packs. A quantity-weighted pack price (sum of line-item value ÷ sum of pack quantity) was used to assess historical price movement for identical ARV presentations, rather than combining unlike medicines into one price comparison. | K25: Recorded commodity value totaled $282.65 million across 35.12 million packs. A quantity-weighted pack price (sum of line-item value ÷ sum of pack quantity) was used to assess historical price movement for identical ARV presentations, rather than combining unlike medicines into one price comparison. | L25: Recorded commodity value totaled $282.65 million across 35.12 million packs. A quantity-weighted pack price (sum of line-item value ÷ sum of pack quantity) was used to assess historical price movement for identical ARV presentations, rather than combining unlike medicines into one price comparison.
B26: Recorded commodity value totaled $282.65 million across 35.12 million packs. A quantity-weighted pack price (sum of line-item value ÷ sum of pack quantity) was used to assess historical price movement for identical ARV presentations, rather than combining unlike medicines into one price comparison. | C26: Recorded commodity value totaled $282.65 million across 35.12 million packs. A quantity-weighted pack price (sum of line-item value ÷ sum of pack quantity) was used to assess historical price movement for identical ARV presentations, rather than combining unlike medicines into one price comparison. | D26: Recorded commodity value totaled $282.65 million across 35.12 million packs. A quantity-weighted pack price (sum of line-item value ÷ sum of pack quantity) was used to assess historical price movement for identical ARV presentations, rather than combining unlike medicines into one price comparison. | E26: Recorded commodity value totaled $282.65 million across 35.12 million packs. A quantity-weighted pack price (sum of line-item value ÷ sum of pack quantity) was used to assess historical price movement for identical ARV presentations, rather than combining unlike medicines into one price comparison. | F26: Recorded commodity value totaled $282.65 million across 35.12 million packs. A quantity-weighted pack price (sum of line-item value ÷ sum of pack quantity) was used to assess historical price movement for identical ARV presentations, rather than combining unlike medicines into one price comparison. | G26: Recorded commodity value totaled $282.65 million across 35.12 million packs. A quantity-weighted pack price (sum of line-item value ÷ sum of pack quantity) was used to assess historical price movement for identical ARV presentations, rather than combining unlike medicines into one price comparison. | H26: Recorded commodity value totaled $282.65 million across 35.12 million packs. A quantity-weighted pack price (sum of line-item value ÷ sum of pack quantity) was used to assess historical price movement for identical ARV presentations, rather than combining unlike medicines into one price comparison. | I26: Recorded commodity value totaled $282.65 million across 35.12 million packs. A quantity-weighted pack price (sum of line-item value ÷ sum of pack quantity) was used to assess historical price movement for identical ARV presentations, rather than combining unlike medicines into one price comparison. | J26: Recorded commodity value totaled $282.65 million across 35.12 million packs. A quantity-weighted pack price (sum of line-item value ÷ sum of pack quantity) was used to assess historical price movement for identical ARV presentations, rather than combining unlike medicines into one price comparison. | K26: Recorded commodity value totaled $282.65 million across 35.12 million packs. A quantity-weighted pack price (sum of line-item value ÷ sum of pack quantity) was used to assess historical price movement for identical ARV presentations, rather than combining unlike medicines into one price comparison. | L26: Recorded commodity value totaled $282.65 million across 35.12 million packs. A quantity-weighted pack price (sum of line-item value ÷ sum of pack quantity) was used to assess historical price movement for identical ARV presentations, rather than combining unlike medicines into one price comparison.
B28: SELECTED HIGH-VALUE ARV PRESENTATION | H28: OBSERVED YEARS | J28: WEIGHTED PACK PRICE (FIRST → LAST)
B29: Lamivudine/Nevirapine/Zidovudine 150/200/300mg, 60 tabs | H29: 2007–2015 | J29: $18.43 → $7.99 (−56.6%)
B30: Efavirenz/Lamivudine/Tenofovir 600/300/300mg, 30 tabs | H30: 2010–2015 | J30: $17.48 → $9.75 (−44.2%)
B31: Efavirenz/Emtricitabine/Tenofovir 600/200/300mg, 30 tabs | H31: 2010–2015 | J31: $19.90 → $11.89 (−40.3%)
B32: Efavirenz 600mg, 30 tabs | H32: 2006–2015 | J32: $16.75 → $3.16 (−81.1%)
B33: Lamivudine/Zidovudine 150/300mg, 60 tabs | H33: 2006–2015 | J33: $11.00 → $6.52 (−40.7%)
B34: COST INTERPRETATION | Major ARV presentations show marked declines in recorded weighted pack prices. This is favorable price-trend evidence, not proof that historical purchases were market-competitive or that the decreases represent realized savings.
B36: 3 RELIABLE SUPPLY
B37: The shipment records support an assessment of distribution dependence and delivery-related supply risks. They cannot directly establish whether patients or facilities experienced stockouts, because demand, inventory balances and facility-level availability are not provided. | C37: The shipment records support an assessment of distribution dependence and delivery-related supply risks. They cannot directly establish whether patients or facilities experienced stockouts, because demand, inventory balances and facility-level availability are not provided. | D37: The shipment records support an assessment of distribution dependence and delivery-related supply risks. They cannot directly establish whether patients or facilities experienced stockouts, because demand, inventory balances and facility-level availability are not provided. | E37: The shipment records support an assessment of distribution dependence and delivery-related supply risks. They cannot directly establish whether patients or facilities experienced stockouts, because demand, inventory balances and facility-level availability are not provided. | F37: The shipment records support an assessment of distribution dependence and delivery-related supply risks. They cannot directly establish whether patients or facilities experienced stockouts, because demand, inventory balances and facility-level availability are not provided. | G37: The shipment records support an assessment of distribution dependence and delivery-related supply risks. They cannot directly establish whether patients or facilities experienced stockouts, because demand, inventory balances and facility-level availability are not provided. | H37: The shipment records support an assessment of distribution dependence and delivery-related supply risks. They cannot directly establish whether patients or facilities experienced stockouts, because demand, inventory balances and facility-level availability are not provided. | I37: The shipment records support an assessment of distribution dependence and delivery-related supply risks. They cannot directly establish whether patients or facilities experienced stockouts, because demand, inventory balances and facility-level availability are not provided. | J37: The shipment records support an assessment of distribution dependence and delivery-related supply risks. They cannot directly establish whether patients or facilities experienced stockouts, because demand, inventory balances and facility-level availability are not provided. | K37: The shipment records support an assessment of distribution dependence and delivery-related supply risks. They cannot directly establish whether patients or facilities experienced stockouts, because demand, inventory balances and facility-level availability are not provided. | L37: The shipment records support an assessment of distribution dependence and delivery-related supply risks. They cannot directly establish whether patients or facilities experienced stockouts, because demand, inventory balances and facility-level availability are not provided.
B38: The shipment records support an assessment of distribution dependence and delivery-related supply risks. They cannot directly establish whether patients or facilities experienced stockouts, because demand, inventory balances and facility-level availability are not provided. | C38: The shipment records support an assessment of distribution dependence and delivery-related supply risks. They cannot directly establish whether patients or facilities experienced stockouts, because demand, inventory balances and facility-level availability are not provided. | D38: The shipment records support an assessment of distribution dependence and delivery-related supply risks. They cannot directly establish whether patients or facilities experienced stockouts, because demand, inventory balances and facility-level availability are not provided. | E38: The shipment records support an assessment of distribution dependence and delivery-related supply risks. They cannot directly establish whether patients or facilities experienced stockouts, because demand, inventory balances and facility-level availability are not provided. | F38: The shipment records support an assessment of distribution dependence and delivery-related supply risks. They cannot directly establish whether patients or facilities experienced stockouts, because demand, inventory balances and facility-level availability are not provided. | G38: The shipment records support an assessment of distribution dependence and delivery-related supply risks. They cannot directly establish whether patients or facilities experienced stockouts, because demand, inventory balances and facility-level availability are not provided. | H38: The shipment records support an assessment of distribution dependence and delivery-related supply risks. They cannot directly establish whether patients or facilities experienced stockouts, because demand, inventory balances and facility-level availability are not provided. | I38: The shipment records support an assessment of distribution dependence and delivery-related supply risks. They cannot directly establish whether patients or facilities experienced stockouts, because demand, inventory balances and facility-level availability are not provided. | J38: The shipment records support an assessment of distribution dependence and delivery-related supply risks. They cannot directly establish whether patients or facilities experienced stockouts, because demand, inventory balances and facility-level availability are not provided. | K38: The shipment records support an assessment of distribution dependence and delivery-related supply risks. They cannot directly establish whether patients or facilities experienced stockouts, because demand, inventory balances and facility-level availability are not provided. | L38: The shipment records support an assessment of distribution dependence and delivery-related supply risks. They cannot directly establish whether patients or facilities experienced stockouts, because demand, inventory balances and facility-level availability are not provided.
B40: MEASURE | E40: EVIDENCE | H40: MANAGEMENT RELEVANCE
B41: RDC commodity-value concentration | E41: $198.48M / $282.65M (70.22%) | H41: A substantial share of recorded commodity value moved through RDC fulfillment.
B42: RDC delivery concentration | E42: 892 / 1,330 deliveries (67.07%) | H42: A majority of evaluated deliveries relied on the RDC channel.
B43: RDC delivery-risk concentration | E43: 161 / 174 late deliveries (92.53%) | H43: Combined distribution concentration and weaker OTD justify a review of routing, scheduling and contingency measures.
B45: PRIORITIZED MANAGEMENT ACTIONS
B46: PRIORITY | D46: EVIDENCE / EXPOSURE | H46: RECOMMENDED MANAGEMENT ACTION
B47: HIGH | D47: RDC: 161 of 174 late deliveries; 81.95% OTD | H47: Review RDC dispatch-to-delivery processes, delay root causes, schedule setting and escalation arrangements.
B48: HIGH | D48: Burundi: 18 late of 35 deliveries (51.43% LTD) | H48: Investigate destination-specific bottlenecks and agree targeted improvement actions; account for limited sample size.
B49: MEDIUM | D49: Aurobindo Direct Drop: 13 late of 105 deliveries | H49: Review the 13 delayed transactions with the relevant logistics and procurement parties; confirm responsibility before corrective action.
B50: MEDIUM | D50: Declining pack prices; no cost or stockout benchmarks | H50: Maintain like-for-like product price monitoring and obtain contracts, inventory and stockout records for fuller assessment.
B52: METHOD, SCOPE & LIMITATIONS
B53: SCOPE | Seven destinations: Burundi, Ethiopia, Kenya, Rwanda, South Sudan, Tanzania and Uganda. The current cleaned workbook contains 1,753 ARV product line items. Delivery metrics are based on 1,330 unique shipment/delivery references.
B54: MEASUREMENT | On time = delivered date ≤ scheduled date. Late delay = delivered date − scheduled date for late deliveries. Weighted pack price = total line-item commodity value / total pack quantity, assessed within matching medicine, strength, formulation and pack size.
B55: LIMITATIONS | RDC commodity value may reflect redistribution rather than new procurement expenditure. Observed supplier/channel differences are associations, not causal evidence. No external price benchmark, procurement contract terms, facility-level demand or stockout series were used.
B57: DATA SOURCE | USAID historical ARV shipment dataset; calculations and dashboard contained in this workbook. Management findings describe the 2006–2015 period only.
